{"ACCUSD":{"icon":{"svg":true,"png":false}},"ETH":{"icon":{"svg":false,"png":true}},"REP":{"icon":{"svg":false,"png":true}},"ADA":{"icon":{"svg":true,"png":false}},"USDT":{"icon":{"svg":true,"png":false}},"ZEC":{"icon":{"svg":false,"png":true}},"ACUSD":{"icon":{"svg":true,"png":false}},"PPGBP":{"icon":{"svg":true,"png":false}},"WMX":{"icon":{"svg":true,"png":false}},"OKGPB":{"icon":{"svg":true,"png":false}},"LQUAH":{"icon":{"svg":true,"png":false}},"DOGE":{"icon":{"svg":false,"png":true}},"LREUR":{"icon":{"svg":true,"png":false}},"BTC":{"icon":{"svg":true,"png":false}},"PMG":{"icon":{"svg":true,"png":false}},"ETC":{"icon":{"svg":false,"png":true}},"LTC":{"icon":{"svg":false,"png":true}},"CUPCNY":{"icon":{"svg":true,"png":false}},"BNB":{"icon":{"svg":true,"png":false}},"BCH":{"icon":{"svg":false,"png":true}},"DASH":{"icon":{"svg":false,"png":true}}}