{"multibank":{"icon":{"svg":false,"png":true},"logo":{"svg":false,"png":true}},"geopaynet_transfer":{"icon":{"svg":true,"png":false},"logo":{"svg":true,"png":false}},"rcbc":{"icon":{"svg":true,"png":false},"logo":{"svg":true,"png":false}},"bank_negara_indonesia":{"icon":{"svg":true,"png":false},"logo":{"svg":true,"png":false}},"busan_bank":{"icon":{"svg":false,"png":true},"logo":{"svg":false,"png":true}},"moneta":{"icon":{"svg":false,"png":true},"logo":{"svg":false,"png":true}},"enetsdirectdebit":{"icon":{"svg":false,"png":true},"logo":{"svg":false,"png":true}},"forexbank":{"icon":{"svg":false,"png":true},"logo":{"svg":false,"png":true}},"ivrbilling":{"icon":{"svg":false,"png":true},"logo":{"svg":false,"png":true}},"csob":{"icon":{"svg":false,"png":true},"logo":{"svg":false,"png":true}},"federal_bank_india":{"icon":{"svg":false,"png":true},"logo":{"svg":false,"png":true}},"skrill":{"icon":{"svg":true,"png":false},"logo":{"svg":true,"png":false}},"airtel_money":{"icon":{"svg":false,"png":true},"logo":{"svg":false,"png":true}},"skandiabanken":{"icon":{"svg":false,"png":true},"logo":{"svg":false,"png":true}},"tescolotus":{"icon":{"svg":false,"png":true},"logo":{"svg":false,"png":true}},"safetypay":{"icon":{"svg":false,"png":true},"logo":{"svg":false,"png":true}},"public_bank_berhad":{"icon":{"svg":false,"png":true},"logo":{"svg":false,"png":true}},"acceptgiro":{"icon":{"svg":false,"png":true},"logo":{"svg":false,"png":true}},"alandsbanken":{"icon":{"svg":false,"png":true},"logo":{"svg":false,"png":true}},"nixmoney":{"icon":{"svg":false,"png":true},"logo":{"svg":false,"png":true}},"banamexdebitcardonlinepaymentmethodmexico":{"icon":{"svg":false,"png":true},"logo":{"svg":false,"png":true}},"olamoney":{"icon":{"svg":false,"png":true},"logo":{"svg":false,"png":true}},"lider":{"icon":{"svg":false,"png":true},"logo":{"svg":false,"png":true}},"karurvysya_bank_india":{"icon":{"svg":true,"png":false},"logo":{"svg":true,"png":false}},"dogecoin":{"icon":{"svg":true,"png":false},"logo":{"svg":true,"png":false}},"sberonline":{"icon":{"svg":true,"png":false},"logo":{"svg":true,"png":false}},"ssk":{"icon":{"svg":false,"png":true},"logo":{"svg":false,"png":true}},"aura":{"icon":{"svg":false,"png":true},"logo":{"svg":false,"png":true}},"247billpay":{"icon":{"svg":false,"png":true},"logo":{"svg":false,"png":true}},"public_bank":{"icon":{"svg":true,"png":false},"logo":{"svg":true,"png":false}},"dcb_bank_india":{"icon":{"svg":false,"png":true},"logo":{"svg":false,"png":true}},"ceskasporitelna":{"icon":{"svg":false,"png":true},"logo":{"svg":false,"png":true}},"siam_commercial_bank":{"icon":{"svg":true,"png":false},"logo":{"svg":true,"png":false}},"privatbank_ssk":{"icon":{"svg":false,"png":true},"logo":{"svg":false,"png":true}},"qqpay":{"icon":{"svg":true,"png":false},"logo":{"svg":true,"png":false}},"futurepay":{"icon":{"svg":false,"png":true},"logo":{"svg":false,"png":true}},"smartmoney":{"icon":{"svg":false,"png":true},"logo":{"svg":false,"png":true}},"bkmexpress":{"icon":{"svg":false,"png":true},"logo":{"svg":false,"png":true}},"commonwealth_bank":{"icon":{"svg":true,"png":false},"logo":{"svg":true,"png":false}},"bancobrasil":{"icon":{"svg":false,"png":true},"logo":{"svg":false,"png":true}},"zimpler":{"icon":{"svg":false,"png":true},"logo":{"svg":false,"png":true}},"kookmin_bank":{"icon":{"svg":true,"png":false},"logo":{"svg":true,"png":false}},"j_k_bank_india":{"icon":{"svg":false,"png":true},"logo":{"svg":false,"png":true}},"kotak_mahindra_bank":{"icon":{"svg":false,"png":true},"logo":{"svg":false,"png":true}},"ticketpremium":{"icon":{"svg":false,"png":true},"logo":{"svg":false,"png":true}},"china_guangfa_bank":{"icon":{"svg":false,"png":true},"logo":{"svg":false,"png":true}},"famsa":{"logo":{"svg":false,"png":true}},"tas24":{"icon":{"svg":false,"png":true}},"paypal":{"icon":{"svg":true,"png":false},"logo":{"svg":true,"png":false}},"advcash_wallet":{"icon":{"svg":true,"png":false},"logo":{"svg":true,"png":false}},"bank_transfer_klarna":{"icon":{"svg":true,"png":false},"logo":{"svg":true,"png":false}},"nordea":{"icon":{"svg":false,"png":true},"logo":{"svg":false,"png":true}},"walletone":{"icon":{"svg":false,"png":true},"logo":{"svg":false,"png":true}},"unionpay_qr":{"icon":{"svg":true,"png":false},"logo":{"svg":true,"png":false}},"account2account":{"icon":{"svg":false,"png":true},"logo":{"svg":false,"png":true}},"bdo":{"icon":{"svg":true,"png":false},"logo":{"svg":true,"png":false}},"bank_rakyat_indonesia":{"icon":{"svg":true,"png":false},"logo":{"svg":true,"png":false}},"farmaciasbenavides":{"icon":{"svg":true,"png":false},"logo":{"svg":true,"png":false}},"osuuspankki":{"icon":{"svg":false,"png":true},"logo":{"svg":false,"png":true}},"china_citic_bank":{"icon":{"svg":true,"png":false},"logo":{"svg":true,"png":false}},"bankofchinanetbanking":{"icon":{"svg":false,"png":true},"logo":{"svg":false,"png":true}},"webmoneytransfer":{"icon":{"svg":true,"png":false},"logo":{"svg":true,"png":false}},"oxxoalternativecashpaymentmethodsmexico":{"icon":{"svg":false,"png":true},"logo":{"svg":false,"png":true}},"americanexpress":{"icon":{"svg":true,"png":false},"logo":{"svg":true,"png":false}},"googlepay":{"icon":{"svg":true,"png":false},"logo":{"svg":true,"png":false}},"ripple":{"icon":{"svg":true,"png":false},"logo":{"svg":true,"png":false}},"sepacredittransfer":{"icon":{"svg":true,"png":false},"logo":{"svg":true,"png":false}},"karnataka_bank":{"icon":{"svg":true,"png":false},"logo":{"svg":true,"png":false}},"masterpass":{"icon":{"svg":false,"png":true},"logo":{"svg":false,"png":true}},"china_postal_savings_bank":{"icon":{"svg":true,"png":false},"logo":{"svg":false,"png":true}},"eps":{"icon":{"svg":false,"png":true},"logo":{"svg":false,"png":true}},"payd":{"icon":{"svg":false,"png":true},"logo":{"svg":false,"png":true}},"kasikornbankkbanknetbanking":{"icon":{"svg":false,"png":true},"logo":{"svg":false,"png":true}},"bank_of_china":{"icon":{"svg":true,"png":false},"logo":{"svg":true,"png":false}},"lakshmi_vilas_bank_india":{"icon":{"svg":false,"png":true},"logo":{"svg":false,"png":true}},"provinciapagos":{"icon":{"svg":false,"png":true},"logo":{"svg":false,"png":true}},"flexepinemoneyvouchers":{"icon":{"svg":false,"png":true},"logo":{"svg":false,"png":true}},"postfinancecard":{"icon":{"svg":false,"png":true},"logo":{"svg":false,"png":true}},"dwolla":{"icon":{"svg":true,"png":false},"logo":{"svg":true,"png":false}},"hipercard":{"icon":{"svg":false,"png":true},"logo":{"svg":false,"png":true}},"bank_central_asia":{"icon":{"svg":true,"png":false},"logo":{"svg":true,"png":false}},"carrierbilling":{"icon":{"svg":false,"png":true},"logo":{"svg":false,"png":true}},"abaqoos":{"icon":{"svg":false,"png":true},"logo":{"svg":false,"png":true}},"yota":{"icon":{"svg":false,"png":true},"logo":{"svg":false,"png":true}},"barzahlen":{"icon":{"svg":false,"png":true},"logo":{"svg":false,"png":true}},"acceptemail":{"icon":{"svg":false,"png":true},"logo":{"svg":false,"png":true}},"7eleven":{"icon":{"svg":false,"png":true},"logo":{"svg":false,"png":true}},"ssk_kz":{"icon":{"svg":false,"png":true},"logo":{"svg":false,"png":true}},"alfaclick":{"icon":{"svg":false,"png":true},"logo":{"svg":false,"png":true}},"cimb_clicks_bank":{"icon":{"svg":false,"png":true},"logo":{"svg":false,"png":true}},"santander":{"icon":{"svg":false,"png":true},"logo":{"svg":false,"png":true}},"perfectmoney_voucher":{"icon":{"svg":true,"png":false},"logo":{"svg":false,"png":true}},"mts":{"icon":{"svg":false,"png":true},"logo":{"svg":false,"png":true}},"mastercard":{"icon":{"svg":true,"png":false},"logo":{"svg":true,"png":false}},"kasikorn_bank":{"icon":{"svg":true,"png":false},"logo":{"svg":true,"png":false}},"bpay":{"icon":{"svg":false,"png":true},"logo":{"svg":false,"png":true}},"visadebit":{"icon":{"svg":false,"png":true},"logo":{"svg":false,"png":true}},"bancsabadell":{"icon":{"svg":false,"png":true},"logo":{"svg":false,"png":true}},"webpayplus":{"icon":{"svg":true,"png":false},"logo":{"svg":true,"png":false}},"selcom":{"icon":{"svg":false,"png":true},"logo":{"svg":false,"png":true}},"perfectmoney":{"icon":{"svg":true,"png":false},"logo":{"svg":false,"png":true}},"sbrebank":{"icon":{"svg":false,"png":true},"logo":{"svg":false,"png":true}},"creditcard":{"icon":{"svg":true,"png":true},"logo":{"svg":true,"png":false}},"fastcheckoutmultisafepay":{"icon":{"svg":false,"png":true},"logo":{"svg":false,"png":true}},"vtb24":{"icon":{"svg":false,"png":true},"logo":{"svg":false,"png":true}},"bancopopular":{"icon":{"svg":false,"png":true},"logo":{"svg":false,"png":true}},"unicredit":{"icon":{"svg":false,"png":true},"logo":{"svg":false,"png":true}},"billink":{"icon":{"svg":false,"png":true},"logo":{"svg":false,"png":true}},"tenpay":{"icon":{"svg":false,"png":true},"logo":{"svg":false,"png":true}},"elo":{"icon":{"svg":false,"png":true},"logo":{"svg":false,"png":true}},"pingping":{"icon":{"svg":false,"png":true},"logo":{"svg":false,"png":true}},"visaelectron":{"icon":{"svg":false,"png":true},"logo":{"svg":false,"png":true}},"standard_charter_bank":{"icon":{"svg":true,"png":false},"logo":{"svg":true,"png":false}},"barpay":{"icon":{"svg":false,"png":true},"logo":{"svg":false,"png":true}},"bigconlinepayment":{"icon":{"svg":false,"png":true},"logo":{"svg":false,"png":true}},"redcompraalternativeonlinepaymentmethodchile":{"icon":{"svg":false,"png":true},"logo":{"svg":false,"png":true}},"bancontactmistercash":{"icon":{"svg":false,"png":true},"logo":{"svg":false,"png":true}},"liqpay":{"icon":{"svg":true,"png":false},"logo":{"svg":true,"png":false}},"uobt":{"icon":{"svg":true,"png":false},"logo":{"svg":true,"png":false}},"erip":{"icon":{"svg":false,"png":true},"logo":{"svg":false,"png":true}},"svyaznoy":{"icon":{"svg":false,"png":true},"logo":{"svg":false,"png":true}},"saastopankki":{"icon":{"svg":false,"png":true},"logo":{"svg":false,"png":true}},"frenchonlinepaymentmethodewalletpaylib":{"icon":{"svg":false,"png":true},"logo":{"svg":false,"png":true}},"coinspaid":{"icon":{"svg":false,"png":true},"logo":{"svg":false,"png":true}},"idfc_bank_india":{"icon":{"svg":true,"png":false},"logo":{"svg":true,"png":false}},"vietcom_bank":{"icon":{"svg":true,"png":false},"logo":{"svg":true,"png":false}},"discover":{"icon":{"svg":true,"png":false},"logo":{"svg":true,"png":false}},"geopaynet":{"icon":{"svg":true,"png":false},"logo":{"svg":true,"png":false}},"standardbank":{"icon":{"svg":false,"png":true},"logo":{"svg":false,"png":true}},"serve":{"icon":{"svg":false,"png":true},"logo":{"svg":false,"png":true}},"postepay":{"icon":{"svg":false,"png":true},"logo":{"svg":false,"png":true}},"zipmark":{"icon":{"svg":false,"png":true},"logo":{"svg":false,"png":true}},"inpay":{"icon":{"svg":false,"png":true},"logo":{"svg":false,"png":true}},"payment_card_token":{"icon":{"svg":true,"png":false},"logo":{"svg":true,"png":false}},"astropaydirect":{"icon":{"svg":true,"png":false},"logo":{"svg":true,"png":false}},"payeer":{"icon":{"svg":false,"png":true},"logo":{"svg":true,"png":false}},"qiwi":{"icon":{"svg":true,"png":false},"logo":{"svg":true,"png":false}},"westpac":{"icon":{"svg":true,"png":false},"logo":{"svg":true,"png":false}},"halo_pesa":{"icon":{"svg":false,"png":true},"logo":{"svg":false,"png":true}},"ssk_ge":{"icon":{"svg":false,"png":true},"logo":{"svg":false,"png":true}},"yandexmoney":{"icon":{"svg":true,"png":false},"logo":{"svg":true,"png":false}},"tarjetanaranjacreditcard":{"icon":{"svg":false,"png":true},"logo":{"svg":false,"png":true}},"industrial_and_commercial_bank_of_china":{"icon":{"svg":true,"png":false},"logo":{"svg":true,"png":false}},"dong_a_bank":{"icon":{"svg":false,"png":true},"logo":{"svg":false,"png":true}},"daegu_bank":{"icon":{"svg":false,"png":true},"logo":{"svg":false,"png":true}},"tarjetaripley":{"icon":{"svg":false,"png":true},"logo":{"svg":false,"png":true}},"privat24":{"icon":{"svg":true,"png":false},"logo":{"svg":true,"png":false}},"nordeasolo":{"icon":{"svg":true,"png":false},"logo":{"svg":true,"png":false}},"cimb_bank":{"icon":{"svg":true,"png":false},"logo":{"svg":true,"png":false}},"elektronischeslastschriftverfahren":{"icon":{"svg":false,"png":true},"logo":{"svg":false,"png":true}},"vubbanka":{"icon":{"svg":false,"png":true},"logo":{"svg":false,"png":true}},"advcash":{"icon":{"svg":true,"png":false},"logo":{"svg":true,"png":false}},"hana_bank":{"icon":{"svg":false,"png":true},"logo":{"svg":false,"png":true}},"bbva":{"icon":{"svg":false,"png":true},"logo":{"svg":false,"png":true}},"scbbanknetbanking":{"icon":{"svg":false,"png":true},"logo":{"svg":false,"png":true}},"idbi_bank":{"icon":{"svg":true,"png":false},"logo":{"svg":true,"png":false}},"hong_leong_bank":{"icon":{"svg":true,"png":false},"logo":{"svg":true,"png":false}},"mir":{"icon":{"svg":true,"png":false},"logo":{"svg":true,"png":false}},"cartebleue":{"icon":{"svg":false,"png":true},"logo":{"svg":false,"png":true}},"bank_card":{"icon":{"svg":true,"png":false},"logo":{"svg":true,"png":false}},"directdebit":{"icon":{"svg":false,"png":true},"logo":{"svg":false,"png":true}},"bdooverthecounterofflinebankdeposit":{"icon":{"svg":false,"png":true},"logo":{"svg":false,"png":true}},"pagofacil":{"icon":{"svg":false,"png":true},"logo":{"svg":false,"png":true}},"agricultural_bank_of_china":{"icon":{"svg":true,"png":false},"logo":{"svg":true,"png":false}},"cartebancaires":{"icon":{"svg":false,"png":true},"logo":{"svg":false,"png":true}},"cartasi":{"icon":{"svg":false,"png":true},"logo":{"svg":false,"png":true}},"tele2ru":{"icon":{"svg":true,"png":false},"logo":{"svg":true,"png":false}},"bancopastor":{"icon":{"svg":false,"png":true},"logo":{"svg":false,"png":true}},"usemyservices":{"icon":{"svg":false,"png":true},"logo":{"svg":false,"png":true}},"banrisulbanricompras":{"icon":{"svg":false,"png":true},"logo":{"svg":false,"png":true}},"icici_bank":{"icon":{"svg":true,"png":false},"logo":{"svg":true,"png":false}},"euteller":{"icon":{"svg":false,"png":true},"logo":{"svg":false,"png":true}},"billsafe":{"icon":{"svg":false,"png":true},"logo":{"svg":false,"png":true}},"ingpl":{"icon":{"svg":true,"png":false},"logo":{"svg":true,"png":false}},"thaimilitarybanktmbnetbanking":{"icon":{"svg":false,"png":true},"logo":{"svg":false,"png":true}},"minitix":{"icon":{"svg":false,"png":true},"logo":{"svg":false,"png":true}},"ibox":{"icon":{"svg":true,"png":false},"logo":{"svg":true,"png":false}},"otpbank":{"icon":{"svg":false,"png":true},"logo":{"svg":false,"png":true}},"cosmos_bank_india":{"icon":{"svg":false,"png":true},"logo":{"svg":false,"png":true}},"sencillito":{"icon":{"svg":true,"png":false},"logo":{"svg":true,"png":false}},"canara_bank":{"icon":{"svg":true,"png":false},"logo":{"svg":true,"png":false}},"test":{"icon":{"svg":true,"png":false},"logo":{"svg":false,"png":true}},"hdfc_bank":{"icon":{"svg":true,"png":false},"logo":{"svg":true,"png":false}},"vvvgiftcard":{"icon":{"svg":false,"png":true},"logo":{"svg":false,"png":true}},"belfiusdirectnet":{"icon":{"svg":false,"png":true},"logo":{"svg":false,"png":true}},"icicinetbanking":{"icon":{"svg":false,"png":true},"logo":{"svg":false,"png":true}},"clickandbuy":{"icon":{"svg":false,"png":true},"logo":{"svg":false,"png":true}},"ssk_by":{"icon":{"svg":false,"png":true},"logo":{"svg":false,"png":true}},"tapiola":{"icon":{"svg":false,"png":true},"logo":{"svg":false,"png":true}},"dokuwallet":{"icon":{"svg":false,"png":true},"logo":{"svg":false,"png":true}},"btn_bank":{"icon":{"svg":false,"png":true},"logo":{"svg":false,"png":true}},"indian_overseas_bank":{"icon":{"svg":false,"png":true},"logo":{"svg":false,"png":true}},"qazkombank":{"icon":{"svg":false,"png":true},"logo":{"svg":false,"png":true}},"maybanknetbankingphillipines":{"icon":{"svg":false,"png":true},"logo":{"svg":false,"png":true}},"redcompra":{"icon":{"svg":true,"png":false},"logo":{"svg":true,"png":false}},"cabal":{"icon":{"svg":false,"png":true},"logo":{"svg":false,"png":true}},"famsaalternativecashpaymentmethodsmexico":{"icon":{"svg":false,"png":true},"logo":{"svg":false,"png":true}},"vodacom":{"icon":{"svg":false,"png":true},"logo":{"svg":false,"png":true}},"bank_of_baroda":{"icon":{"svg":true,"png":false},"logo":{"svg":true,"png":false}},"cardpay":{"icon":{"svg":true,"png":false},"logo":{"svg":true,"png":false}},"freecharge":{"icon":{"svg":true,"png":false},"logo":{"svg":true,"png":false}},"indian_bank":{"icon":{"svg":true,"png":false},"logo":{"svg":true,"png":false}},"chinaunionpay":{"icon":{"svg":true,"png":false},"logo":{"svg":true,"png":false}},"rupaypaysecure":{"icon":{"svg":false,"png":true},"logo":{"svg":false,"png":true}},"nsmep":{"icon":{"svg":false,"png":true},"logo":{"svg":false,"png":true}},"wmnote":{"icon":{"svg":false,"png":true},"logo":{"svg":false,"png":true}},"afterpay":{"icon":{"svg":false,"png":true},"logo":{"svg":false,"png":true}},"dinersclub":{"icon":{"svg":true,"png":false},"logo":{"svg":true,"png":false}},"presto":{"icon":{"svg":false,"png":true},"logo":{"svg":false,"png":true}},"billpay":{"icon":{"svg":false,"png":true},"logo":{"svg":false,"png":true}},"Self service kiosk South Africa":{"icon":{"svg":false,"png":true},"logo":{"svg":false,"png":true}},"inteligo":{"icon":{"svg":false,"png":true},"logo":{"svg":false,"png":true}},"Self service kiosk Ukraine":{"icon":{"svg":false,"png":true},"logo":{"svg":false,"png":true}},"giropay":{"icon":{"svg":true,"png":false},"logo":{"svg":true,"png":false}},"mbank":{"icon":{"svg":false,"png":true},"logo":{"svg":false,"png":true}},"interkassa":{"icon":{"svg":true,"png":false},"logo":{"svg":true,"png":false}},"paytm":{"icon":{"svg":true,"png":false},"logo":{"svg":true,"png":false}},"pagoefectivo":{"icon":{"svg":false,"png":true},"logo":{"svg":false,"png":true}},"bankaxess":{"icon":{"svg":false,"png":true},"logo":{"svg":false,"png":true}},"industrial_bank_of_korea":{"icon":{"svg":true,"png":false},"logo":{"svg":true,"png":false}},"bangkokbanknetbanking":{"icon":{"svg":false,"png":true},"logo":{"svg":false,"png":true}},"smsbilling":{"icon":{"svg":false,"png":true},"logo":{"svg":false,"png":true}},"russianpost":{"icon":{"svg":false,"png":true},"logo":{"svg":false,"png":true}},"piastrix":{"icon":{"svg":true,"png":false},"logo":{"svg":true,"png":false}},"ssk_ua":{"icon":{"svg":false,"png":true},"logo":{"svg":false,"png":true}},"dhanalaxmi_bank_india":{"icon":{"svg":false,"png":true},"logo":{"svg":false,"png":true}},"zapp":{"icon":{"svg":false,"png":true},"logo":{"svg":false,"png":true}},"oppohjola":{"icon":{"svg":false,"png":true},"logo":{"svg":false,"png":true}},"kriita2":{"icon":{"svg":false,"png":true},"logo":{"svg":false,"png":true}},"china_merchants_bank":{"icon":{"svg":true,"png":false},"logo":{"svg":true,"png":false}},"inghomepay":{"icon":{"svg":false,"png":true},"logo":{"svg":false,"png":true}},"paymer":{"icon":{"svg":false,"png":true},"logo":{"svg":false,"png":true}},"punjab_national_bank":{"icon":{"svg":true,"png":false},"logo":{"svg":true,"png":false}},"papercheck":{"icon":{"svg":false,"png":true},"logo":{"svg":false,"png":true}},"sebbank":{"icon":{"svg":false,"png":true},"logo":{"svg":false,"png":true}},"zantel_ezypesa":{"icon":{"svg":false,"png":true},"logo":{"svg":false,"png":true}},"china_everbright_bank":{"icon":{"svg":true,"png":false},"logo":{"svg":true,"png":false}},"exmo":{"icon":{"svg":false,"png":true},"logo":{"svg":false,"png":true}},"bancoitau":{"icon":{"svg":false,"png":true},"logo":{"svg":false,"png":true}},"yes_bank":{"icon":{"svg":true,"png":false},"logo":{"svg":true,"png":false}},"gcashwallet":{"icon":{"svg":false,"png":true},"logo":{"svg":false,"png":true}},"bank_of_india":{"icon":{"svg":true,"png":false},"logo":{"svg":true,"png":false}},"paynearme":{"icon":{"svg":false,"png":true},"logo":{"svg":false,"png":true}},"aktia":{"icon":{"svg":false,"png":true},"logo":{"svg":false,"png":true}},"visacheckout":{"icon":{"svg":false,"png":true},"logo":{"svg":false,"png":true}},"upi_aggregated":{"icon":{"svg":true,"png":false},"logo":{"svg":true,"png":false}},"ecobanq":{"icon":{"svg":false,"png":true},"logo":{"svg":false,"png":true}},"megafon":{"icon":{"svg":false,"png":true},"logo":{"svg":false,"png":true}},"russian_standart_bank":{"icon":{"svg":false,"png":true},"logo":{"svg":false,"png":true}},"national_australia_bank":{"icon":{"svg":true,"png":false},"logo":{"svg":true,"png":false}},"teleingreso":{"icon":{"svg":false,"png":true},"logo":{"svg":false,"png":true}},"przelewy24":{"icon":{"svg":false,"png":true},"logo":{"svg":false,"png":true}},"banktransfer":{"icon":{"svg":true,"png":false},"logo":{"svg":true,"png":true}},"state_bank_of_india":{"icon":{"svg":true,"png":false},"logo":{"svg":true,"png":false}},"tigo_pesa":{"icon":{"svg":false,"png":true},"logo":{"svg":false,"png":true}},"efectyonlinecashpaymentmethodscolombia":{"icon":{"svg":false,"png":true},"logo":{"svg":false,"png":true}},"creditagricole":{"icon":{"svg":false,"png":true},"logo":{"svg":false,"png":true}},"bri_bank":{"icon":{"svg":true,"png":false},"logo":{"svg":true,"png":false}},"billmelater":{"icon":{"svg":false,"png":true},"logo":{"svg":false,"png":true}},"china_union_pay":{"icon":{"svg":true,"png":false},"logo":{"svg":true,"png":false}},"rhb_bank":{"icon":{"svg":true,"png":false},"logo":{"svg":true,"png":false}},"payfastwallet":{"icon":{"svg":false,"png":true},"logo":{"svg":false,"png":true}},"mastercarddebit":{"icon":{"svg":false,"png":true},"logo":{"svg":false,"png":true}},"tether":{"icon":{"svg":true,"png":false},"logo":{"svg":true,"png":false}},"maestro":{"icon":{"svg":true,"png":false},"logo":{"svg":true,"png":false}},"webpaypluscreditcardsonlinepaymentsolutionchile":{"icon":{"svg":false,"png":true},"logo":{"svg":false,"png":true}},"korea_development_bank":{"icon":{"svg":false,"png":true},"logo":{"svg":false,"png":true}},"viabalotoonline":{"icon":{"svg":true,"png":false},"logo":{"svg":true,"png":false}},"mypaywizard":{"icon":{"svg":false,"png":true},"logo":{"svg":false,"png":true}},"rbkmoney":{"icon":{"svg":false,"png":true},"logo":{"svg":false,"png":true}},"ideal":{"icon":{"svg":true,"png":false},"logo":{"svg":true,"png":false}},"kwangju_bank":{"icon":{"svg":false,"png":true},"logo":{"svg":false,"png":true}},"ukash":{"icon":{"svg":false,"png":true},"logo":{"svg":false,"png":true}},"euroset":{"icon":{"svg":false,"png":true},"logo":{"svg":false,"png":true}},"paysbuy":{"icon":{"svg":false,"png":true},"logo":{"svg":false,"png":true}},"applepay":{"icon":{"svg":true,"png":false},"logo":{"svg":true,"png":false}},"justpayewallet":{"icon":{"svg":false,"png":true},"logo":{"svg":false,"png":true}},"cimb_clicks_indonesia":{"icon":{"svg":false,"png":true},"logo":{"svg":false,"png":true}},"visa2":{"icon":{"svg":false,"png":true},"logo":{"svg":false,"png":true}},"jcb":{"icon":{"svg":false,"png":true},"logo":{"svg":false,"png":true}},"permata_bank":{"icon":{"svg":true,"png":false},"logo":{"svg":true,"png":false}},"resursbank":{"icon":{"svg":true,"png":false},"logo":{"svg":true,"png":false}},"union_bank_of_india":{"icon":{"svg":true,"png":false},"logo":{"svg":true,"png":false}},"wupay":{"icon":{"svg":false,"png":true},"logo":{"svg":false,"png":true}},"china_minsheng_bank":{"icon":{"svg":true,"png":false},"logo":{"svg":false,"png":true}},"krung_thai_bank":{"icon":{"svg":true,"png":false},"logo":{"svg":true,"png":false}},"swedbank":{"icon":{"svg":false,"png":true},"logo":{"svg":false,"png":true}},"viabalotoonlinecashpaymentmethodscolombia":{"icon":{"svg":false,"png":true},"logo":{"svg":false,"png":true}},"ukrsibbank":{"icon":{"svg":false,"png":true},"logo":{"svg":false,"png":true}},"uatp":{"icon":{"svg":false,"png":true},"logo":{"svg":false,"png":true}},"astropaymanual":{"icon":{"svg":true,"png":false},"logo":{"svg":true,"png":false}},"astropayunion":{"icon":{"svg":true,"png":false},"logo":{"svg":true,"png":false}},"slovenskasporitelna":{"icon":{"svg":false,"png":true},"logo":{"svg":false,"png":true}},"advcash_wallet_email":{"icon":{"svg":true,"png":false},"logo":{"svg":true,"png":false}},"icabanken":{"icon":{"svg":false,"png":true},"logo":{"svg":false,"png":true}},"bidv_bank":{"icon":{"svg":true,"png":false},"logo":{"svg":true,"png":false}},"litecoin":{"icon":{"svg":false,"png":true},"logo":{"svg":false,"png":true}},"visa_mastercard":{"icon":{"svg":false,"png":true}},"rcbcoverthecounteronlinebankdeposit":{"icon":{"svg":false,"png":true},"logo":{"svg":false,"png":true}},"farmaciasbenavidesalternativecashpaymentmethodsmexico":{"icon":{"svg":false,"png":true},"logo":{"svg":false,"png":true}},"tatrabanka":{"icon":{"svg":false,"png":true},"logo":{"svg":false,"png":true}},"toditocash":{"icon":{"svg":false,"png":true},"logo":{"svg":false,"png":true}},"polipayonline":{"icon":{"svg":false,"png":true},"logo":{"svg":false,"png":true}},"vmevisa":{"icon":{"svg":false,"png":true},"logo":{"svg":false,"png":true}},"krungthaibanknetbanking":{"icon":{"svg":false,"png":true},"logo":{"svg":false,"png":true}},"farmaciasdelahorro":{"icon":{"svg":true,"png":false},"logo":{"svg":true,"png":false}},"paysafecard":{"icon":{"svg":true,"png":false},"logo":{"svg":true,"png":false}},"ciberpay":{"icon":{"svg":false,"png":true},"logo":{"svg":false,"png":true}},"sencillitoalternativecashpaymentmethodschile":{"icon":{"svg":false,"png":true},"logo":{"svg":false,"png":true}},"neteller":{"icon":{"svg":false,"png":true},"logo":{"svg":true,"png":false}},"bitcoin_cash":{"icon":{"svg":false,"png":true},"logo":{"svg":false,"png":true}},"vpay":{"icon":{"svg":false,"png":true},"logo":{"svg":false,"png":true}},"ethereum":{"icon":{"svg":true,"png":false},"logo":{"svg":true,"png":false}},"kbcbetaalknop":{"icon":{"svg":false,"png":true},"logo":{"svg":false,"png":true}},"payment_card":{"icon":{"svg":true,"png":false},"logo":{"svg":true,"png":false}},"pagseguro":{"icon":{"svg":false,"png":true},"logo":{"svg":false,"png":true}},"onecard":{"icon":{"svg":false,"png":true},"logo":{"svg":false,"png":true}},"postovabanka":{"icon":{"svg":false,"png":true},"logo":{"svg":false,"png":true}},"visa":{"icon":{"svg":true,"png":false},"logo":{"svg":true,"png":false}},"nonghyup_bank":{"icon":{"svg":false,"png":true},"logo":{"svg":false,"png":true}},"girocard":{"icon":{"svg":false,"png":true},"logo":{"svg":false,"png":true}},"neosurf":{"icon":{"svg":false,"png":true},"logo":{"svg":false,"png":true}},"mybank2":{"icon":{"svg":false,"png":true},"logo":{"svg":false,"png":true}},"paydirektalternativepaymentmethodgermany":{"icon":{"svg":false,"png":true},"logo":{"svg":false,"png":true}},"argencard":{"icon":{"svg":false,"png":true},"logo":{"svg":false,"png":true}},"mazooma":{"icon":{"svg":false,"png":true},"logo":{"svg":false,"png":true}},"kviku":{"icon":{"svg":false,"png":true},"logo":{"svg":false,"png":true}},"acb_bank":{"icon":{"svg":true,"png":false},"logo":{"svg":true,"png":false}},"card":{"icon":{"svg":true,"png":true},"logo":{"svg":true,"png":false}},"perfectmoney_account":{"icon":{"svg":true,"png":false},"logo":{"svg":false,"png":true}},"bankinter":{"icon":{"svg":false,"png":true},"logo":{"svg":false,"png":true}},"primabanka":{"icon":{"svg":false,"png":true},"logo":{"svg":false,"png":true}},"Self service kiosk Russia":{"icon":{"svg":false,"png":true},"logo":{"svg":false,"png":true}},"rapidtransfer":{"icon":{"svg":false,"png":true},"logo":{"svg":false,"png":true}},"beeline":{"icon":{"svg":false,"png":true},"logo":{"svg":false,"png":true}},"citadelelatvia":{"icon":{"svg":false,"png":true},"logo":{"svg":false,"png":true}},"postpay":{"icon":{"svg":false,"png":true},"logo":{"svg":false,"png":true}},"epese":{"icon":{"svg":false,"png":true},"logo":{"svg":false,"png":true}},"danskebank":{"icon":{"svg":false,"png":true},"logo":{"svg":false,"png":true}},"shinhan_bank":{"icon":{"svg":true,"png":false},"logo":{"svg":true,"png":false}},"spankki":{"icon":{"svg":false,"png":true},"logo":{"svg":false,"png":true}},"danamon_bank":{"icon":{"svg":false,"png":true},"logo":{"svg":false,"png":true}},"magna":{"icon":{"svg":true,"png":false},"logo":{"svg":true,"png":false}},"bitcoin":{"icon":{"svg":true,"png":false},"logo":{"svg":true,"png":false}},"paybybill":{"icon":{"svg":false,"png":true},"logo":{"svg":false,"png":true}},"binance_coin":{"icon":{"svg":true,"png":false},"logo":{"svg":true,"png":false}},"handelsbanken":{"icon":{"svg":false,"png":true},"logo":{"svg":false,"png":true}},"bank_of_communication":{"icon":{"svg":true,"png":false},"logo":{"svg":true,"png":false}},"banamex":{"icon":{"svg":true,"png":false},"logo":{"svg":true,"png":false}},"mpayaisthailand":{"icon":{"svg":false,"png":true},"logo":{"svg":false,"png":true}},"ekonto":{"icon":{"svg":false,"png":true},"logo":{"svg":false,"png":true}},"ssk_md":{"icon":{"svg":false,"png":true},"logo":{"svg":false,"png":true}},"woori_bank":{"icon":{"svg":false,"png":true},"logo":{"svg":false,"png":true}},"erstebank":{"icon":{"svg":false,"png":true},"logo":{"svg":false,"png":true}},"unitedoverseasbankuobnetbanking":{"icon":{"svg":false,"png":true},"logo":{"svg":false,"png":true}},"bancodobrasil":{"icon":{"svg":true,"png":false},"logo":{"svg":true,"png":false}},"paydirekt":{"icon":{"svg":true,"png":false},"logo":{"svg":true,"png":false}},"uax":{"icon":{"svg":true,"png":false},"logo":{"svg":true,"png":false}},"raiffeisenbank":{"icon":{"svg":true,"png":false},"logo":{"svg":true,"png":false}},"rixty":{"icon":{"svg":false,"png":true},"logo":{"svg":false,"png":true}},"servipag":{"icon":{"svg":false,"png":true},"logo":{"svg":false,"png":true}},"kievstar":{"icon":{"svg":false,"png":true},"logo":{"svg":false,"png":true}},"vcreditos":{"icon":{"svg":true,"png":false},"logo":{"svg":true,"png":false}},"bangko_bank":{"icon":{"svg":true,"png":false},"logo":{"svg":true,"png":false}},"krungsrinetbanking":{"icon":{"svg":false,"png":true},"logo":{"svg":false,"png":true}},"rapipago":{"icon":{"svg":false,"png":true},"logo":{"svg":false,"png":true}},"onlinenaira":{"icon":{"svg":false,"png":true},"logo":{"svg":false,"png":true}},"peela":{"icon":{"svg":false,"png":true},"logo":{"svg":false,"png":true}},"poppankki":{"icon":{"svg":false,"png":true},"logo":{"svg":false,"png":true}},"citibank_korea":{"icon":{"svg":true,"png":false},"logo":{"svg":true,"png":false}},"milleniumbank":{"icon":{"svg":false,"png":true},"logo":{"svg":false,"png":true}},"instantcredit":{"icon":{"svg":false,"png":true},"logo":{"svg":false,"png":true}},"kwixo":{"icon":{"svg":false,"png":true},"logo":{"svg":false,"png":true}},"mg_bank_saemmul":{"icon":{"svg":false,"png":true},"logo":{"svg":false,"png":true}},"interac":{"icon":{"svg":false,"png":true},"logo":{"svg":false,"png":true}},"moneytopay":{"icon":{"svg":false,"png":true},"logo":{"svg":false,"png":true}},"octopus":{"icon":{"svg":false,"png":true},"logo":{"svg":false,"png":true}},"farmaciasdelahorroalternativecashpaymentmethodsmexico":{"icon":{"svg":false,"png":true},"logo":{"svg":false,"png":true}},"papaya":{"icon":{"svg":false,"png":true},"logo":{"svg":false,"png":true}},"tamilnad_mercantile_bank_india":{"icon":{"svg":false,"png":true},"logo":{"svg":false,"png":true}},"lacaixa":{"icon":{"svg":false,"png":true},"logo":{"svg":false,"png":true}},"jyskebank":{"icon":{"svg":false,"png":true},"logo":{"svg":false,"png":true}},"wechat":{"icon":{"svg":true,"png":false},"logo":{"svg":true,"png":false}},"bankzachodniwbk":{"icon":{"svg":false,"png":true},"logo":{"svg":false,"png":true}},"hdfcbanknetbankingindia":{"icon":{"svg":false,"png":true},"logo":{"svg":false,"png":true}},"mminvoicing":{"icon":{"svg":false,"png":true},"logo":{"svg":false,"png":true}},"debitobradesco":{"icon":{"svg":false,"png":true},"logo":{"svg":false,"png":true}},"reliance_jio":{"icon":{"svg":true,"png":false},"logo":{"svg":true,"png":false}},"sofortbanking":{"icon":{"svg":true,"png":false},"logo":{"svg":true,"png":false}},"trustly":{"icon":{"svg":false,"png":true},"logo":{"svg":false,"png":true}},"techom_bank":{"icon":{"svg":true,"png":false},"logo":{"svg":true,"png":false}},"indusind_bank":{"icon":{"svg":false,"png":true},"logo":{"svg":false,"png":true}},"shanghai_pudong_development_bank":{"icon":{"svg":true,"png":false},"logo":{"svg":false,"png":true}},"viber":{"icon":{"svg":false,"png":true},"logo":{"svg":false,"png":true}},"bancodobrasilcomercioeletronico":{"icon":{"svg":false,"png":true},"logo":{"svg":false,"png":true}},"Self service kiosk Moldova":{"icon":{"svg":false,"png":true},"logo":{"svg":false,"png":true}},"ssk_ru":{"icon":{"svg":false,"png":true},"logo":{"svg":false,"png":true}},"ingspain":{"icon":{"svg":false,"png":true},"logo":{"svg":false,"png":true}},"swift":{"icon":{"svg":true,"png":false},"logo":{"svg":true,"png":false}},"mandiri_bank":{"icon":{"svg":true,"png":false},"logo":{"svg":true,"png":false}},"ping_an_bank":{"icon":{"svg":true,"png":false},"logo":{"svg":true,"png":false}},"industrial_bank":{"icon":{"svg":true,"png":false},"logo":{"svg":true,"png":false}},"psbretail":{"icon":{"svg":false,"png":true},"logo":{"svg":false,"png":true}},"efecty":{"icon":{"svg":true,"png":false},"logo":{"svg":true,"png":false}},"standard_chartered_bank_korea":{"icon":{"svg":true,"png":false},"logo":{"svg":true,"png":false}},"moneymail":{"icon":{"svg":false,"png":true},"logo":{"svg":false,"png":true}},"electroniccheckach":{"icon":{"svg":false,"png":true},"logo":{"svg":false,"png":true}},"volksbank":{"icon":{"svg":false,"png":true},"logo":{"svg":false,"png":true}},"fakturaru":{"icon":{"svg":false,"png":true},"logo":{"svg":false,"png":true}},"Self service kiosk Belarus":{"icon":{"svg":false,"png":true},"logo":{"svg":false,"png":true}},"deutsche_bank_india":{"icon":{"svg":false,"png":true},"logo":{"svg":false,"png":true}},"china_construction_bank":{"icon":{"svg":true,"png":false},"logo":{"svg":true,"png":false}},"payshop":{"icon":{"svg":false,"png":true},"logo":{"svg":false,"png":true}},"paysafecash":{"icon":{"svg":true,"png":false},"logo":{"svg":true,"png":false}},"ecopayz":{"icon":{"svg":true,"png":false},"logo":{"svg":true,"png":false}},"capayable":{"icon":{"svg":false,"png":true},"logo":{"svg":false,"png":true}},"komercnibanka":{"icon":{"svg":false,"png":true},"logo":{"svg":false,"png":true}},"mobikwik":{"icon":{"svg":false,"png":true},"logo":{"svg":false,"png":true}},"multibanconet":{"icon":{"svg":false,"png":true},"logo":{"svg":false,"png":true}},"viabill":{"icon":{"svg":false,"png":true},"logo":{"svg":false,"png":true}},"cifrograd":{"icon":{"svg":false,"png":true},"logo":{"svg":false,"png":true}},"everi":{"icon":{"svg":false,"png":true},"logo":{"svg":false,"png":true}},"octopuscardonlinepaymentservice":{"icon":{"svg":false,"png":true},"logo":{"svg":false,"png":true}},"pravexbank":{"icon":{"svg":false,"png":true},"logo":{"svg":false,"png":true}},"okpay":{"icon":{"svg":false,"png":true},"logo":{"svg":false,"png":true}},"lansforsakringar":{"icon":{"svg":false,"png":true},"logo":{"svg":false,"png":true}},"astropaycash":{"icon":{"svg":true,"png":false},"logo":{"svg":true,"png":false}},"cellularworld":{"icon":{"svg":false,"png":true},"logo":{"svg":false,"png":true}},"krungsri":{"icon":{"svg":false,"png":true},"logo":{"svg":false,"png":true}},"gemoney":{"icon":{"svg":false,"png":true},"logo":{"svg":false,"png":true}},"cashu":{"icon":{"svg":false,"png":true},"logo":{"svg":false,"png":true}},"postfinanceefinance":{"icon":{"svg":false,"png":true},"logo":{"svg":false,"png":true}},"mercadopago":{"icon":{"svg":false,"png":true},"logo":{"svg":false,"png":true}},"libertybank":{"icon":{"svg":false,"png":true},"logo":{"svg":false,"png":true}},"wmcard":{"icon":{"svg":false,"png":true},"logo":{"svg":false,"png":true}},"shamrao_vithal_cooperative_bank_india":{"icon":{"svg":false,"png":true},"logo":{"svg":false,"png":true}},"cimbclicksinternetbanking":{"icon":{"svg":false,"png":true},"logo":{"svg":false,"png":true}},"ssk_za":{"icon":{"svg":false,"png":true},"logo":{"svg":false,"png":true}},"bancnetdirectdebits":{"icon":{"svg":false,"png":true},"logo":{"svg":false,"png":true}},"sepadirectdebit":{"icon":{"svg":true,"png":false},"logo":{"svg":true,"png":false}},"epaybg":{"icon":{"svg":true,"png":false},"logo":{"svg":true,"png":false}},"magnacreditcardsonlinepaymentmethodschile":{"icon":{"svg":false,"png":true},"logo":{"svg":false,"png":true}},"banklink":{"icon":{"svg":false,"png":true},"logo":{"svg":false,"png":true}},"tranzzo":{"icon":{"svg":false,"png":true},"logo":{"svg":false,"png":true}},"australia_and_new_zealand_banking_group":{"icon":{"svg":true,"png":false},"logo":{"svg":true,"png":false}},"south_indian_bank":{"icon":{"svg":false,"png":true},"logo":{"svg":false,"png":true}},"wiretransfer":{"icon":{"svg":true,"png":false},"logo":{"svg":true,"png":false}},"pagorapido":{"icon":{"svg":false,"png":true},"logo":{"svg":false,"png":true}},"achdebits":{"icon":{"svg":false,"png":true},"logo":{"svg":false,"png":true}},"coingate":{"icon":{"svg":true,"png":false},"logo":{"svg":true,"png":false}},"vietin_bank":{"icon":{"svg":false,"png":true},"logo":{"svg":false,"png":true}},"central_bank_of_india":{"icon":{"svg":false,"png":true},"logo":{"svg":false,"png":true}},"Self service kiosk Tajikistan":{"icon":{"svg":false,"png":true},"logo":{"svg":false,"png":true}},"muchbetter":{"icon":{"svg":true,"png":false},"logo":{"svg":true,"png":false}},"exim_bank":{"icon":{"svg":true,"png":false},"logo":{"svg":true,"png":false}},"promsvyazbank":{"icon":{"svg":false,"png":true},"logo":{"svg":false,"png":true}},"easypay":{"icon":{"svg":false,"png":true},"logo":{"svg":false,"png":true}},"privatbank":{"icon":{"svg":true,"png":false},"logo":{"svg":true,"png":false}},"asdasda":{"logo":{"svg":true,"png":true}},"epayua":{"icon":{"svg":false,"png":true},"logo":{"svg":false,"png":true}},"phonepe":{"icon":{"svg":true,"png":false},"logo":{"svg":true,"png":false}},"oxxo":{"icon":{"svg":true,"png":false},"logo":{"svg":true,"png":false}},"alipay":{"icon":{"svg":true,"png":false},"logo":{"svg":true,"png":false}},"bankia":{"icon":{"svg":false,"png":true},"logo":{"svg":false,"png":true}},"cash":{"icon":{"svg":true,"png":true},"logo":{"svg":true,"png":true}},"tinkoff":{"icon":{"svg":false,"png":true},"logo":{"svg":false,"png":true}},"maharashtra_bank_india":{"icon":{"svg":true,"png":false},"logo":{"svg":true,"png":false}},"googlewallet":{"icon":{"svg":true,"png":false},"logo":{"svg":true,"png":false}},"liqpay_wallet":{"icon":{"svg":true,"png":false},"logo":{"svg":true,"png":false}},"dankort":{"icon":{"svg":false,"png":true},"logo":{"svg":false,"png":true}},"unistream":{"icon":{"svg":false,"png":true},"logo":{"svg":false,"png":true}},"ssk_tj":{"icon":{"svg":false,"png":true},"logo":{"svg":false,"png":true}},"axis_bank":{"icon":{"svg":true,"png":false},"logo":{"svg":true,"png":false}},"sacom_bank":{"icon":{"svg":false,"png":true},"logo":{"svg":false,"png":true}},"payzippy":{"icon":{"svg":false,"png":true},"logo":{"svg":false,"png":true}},"may_bank":{"icon":{"svg":true,"png":false},"logo":{"svg":true,"png":false}},"bradescocomercioeletronico":{"icon":{"svg":false,"png":true},"logo":{"svg":false,"png":true}},"uco_bank_india":{"icon":{"svg":false,"png":true},"logo":{"svg":false,"png":true}},"boletobancariopay":{"icon":{"svg":false,"png":true},"logo":{"svg":false,"png":true}},"ecoineu":{"icon":{"svg":false,"png":true},"logo":{"svg":false,"png":true}}}