{"bankinter":{"icon":{"svg":false,"png":true},"logo":{"svg":false,"png":true}},"inteligo":{"icon":{"svg":false,"png":true},"logo":{"svg":false,"png":true}},"moneymail":{"icon":{"svg":false,"png":true},"logo":{"svg":false,"png":true}},"banrisulbanricompras":{"icon":{"svg":false,"png":true},"logo":{"svg":false,"png":true}},"visacheckout":{"icon":{"svg":false,"png":true},"logo":{"svg":false,"png":true}},"liqpay_aggregated":{"icon":{"svg":false,"png":true},"logo":{"svg":true,"png":false}},"applepay":{"icon":{"svg":false,"png":true},"logo":{"svg":false,"png":true}},"bancontactmistercash":{"icon":{"svg":false,"png":true},"logo":{"svg":false,"png":true}},"sencillitoalternativecashpaymentmethodschile":{"icon":{"svg":false,"png":true},"logo":{"svg":false,"png":true}},"ingspain":{"icon":{"svg":false,"png":true},"logo":{"svg":false,"png":true}},"capayable":{"icon":{"svg":false,"png":true},"logo":{"svg":false,"png":true}},"skrill2":{"icon":{"svg":false,"png":true},"logo":{"svg":false,"png":true}},"litecoin":{"icon":{"svg":false,"png":true},"logo":{"svg":false,"png":true}},"paybybill":{"icon":{"svg":false,"png":true},"logo":{"svg":false,"png":true}},"Self service kiosk Tajikistan":{"icon":{"svg":false,"png":true},"logo":{"svg":false,"png":true}},"giropay":{"icon":{"svg":false,"png":true},"logo":{"svg":false,"png":true}},"euroset":{"icon":{"svg":false,"png":true}},"belfiusdirectnet":{"icon":{"svg":false,"png":true},"logo":{"svg":false,"png":true}},"sepacredittransfer":{"icon":{"svg":false,"png":true},"logo":{"svg":false,"png":true}},"chinaunionpay":{"icon":{"svg":false,"png":true},"logo":{"svg":false,"png":true}},"bbva":{"icon":{"svg":false,"png":true},"logo":{"svg":false,"png":true}},"standardbank":{"icon":{"svg":false,"png":true},"logo":{"svg":false,"png":true}},"kviku":{"icon":{"svg":false,"png":true},"logo":{"svg":false,"png":true}},"beeline":{"icon":{"svg":false,"png":true},"logo":{"svg":false,"png":true}},"abaqoos":{"icon":{"svg":false,"png":true},"logo":{"svg":false,"png":true}},"handelsbanken":{"icon":{"svg":false,"png":true},"logo":{"svg":false,"png":true}},"sberonline":{"logo":{"svg":false,"png":true},"icon":{"svg":true,"png":false}},"nordea":{"icon":{"svg":false,"png":true},"logo":{"svg":false,"png":true}},"citadelelatvia":{"icon":{"svg":false,"png":true},"logo":{"svg":false,"png":true}},"paypal":{"icon":{"svg":false,"png":true},"logo":{"svg":false,"png":true}},"everi":{"icon":{"svg":false,"png":true},"logo":{"svg":false,"png":true}},"dokuwallet":{"icon":{"svg":false,"png":true},"logo":{"svg":false,"png":true}},"neteller":{"icon":{"svg":false,"png":true},"logo":{"svg":false,"png":true}},"smsbilling":{"icon":{"svg":false,"png":true},"logo":{"svg":false,"png":true}},"payshop":{"icon":{"svg":false,"png":true},"logo":{"svg":false,"png":true}},"papaya":{"icon":{"svg":false,"png":true},"logo":{"svg":false,"png":true}},"visa_mastercard":{"icon":{"svg":false,"png":true}},"onecard":{"icon":{"svg":false,"png":true},"logo":{"svg":false,"png":true}},"spankki":{"icon":{"svg":false,"png":true},"logo":{"svg":false,"png":true}},"megafon":{"icon":{"svg":false,"png":true},"logo":{"svg":false,"png":true}},"dankort":{"icon":{"svg":false,"png":true},"logo":{"svg":false,"png":true}},"hdfcbanknetbankingindia":{"icon":{"svg":false,"png":true},"logo":{"svg":false,"png":true}},"cartebancaires":{"icon":{"svg":false,"png":true},"logo":{"svg":false,"png":true}},"bradescocomercioeletronico":{"icon":{"svg":false,"png":true},"logo":{"svg":false,"png":true}},"alfaclick":{"icon":{"svg":false,"png":true}},"octopuscardonlinepaymentservice":{"icon":{"svg":false,"png":true},"logo":{"svg":false,"png":true}},"alipay":{"icon":{"svg":false,"png":true},"logo":{"svg":false,"png":true}},"directdebit":{"icon":{"svg":false,"png":true},"logo":{"svg":false,"png":true}},"rcbcoverthecounteronlinebankdeposit":{"icon":{"svg":false,"png":true},"logo":{"svg":false,"png":true}},"creditcard":{"icon":{"svg":true,"png":true},"logo":{"svg":true,"png":false}},"argencard":{"icon":{"svg":false,"png":true},"logo":{"svg":false,"png":true}},"tatrabanka":{"icon":{"svg":false,"png":true},"logo":{"svg":false,"png":true}},"trustly":{"icon":{"svg":false,"png":true},"logo":{"svg":false,"png":true}},"mbank":{"icon":{"svg":false,"png":true},"logo":{"svg":false,"png":true}},"acceptemail":{"icon":{"svg":false,"png":true},"logo":{"svg":false,"png":true}},"postfinanceefinance":{"icon":{"svg":false,"png":true},"logo":{"svg":false,"png":true}},"alandsbanken":{"icon":{"svg":false,"png":true},"logo":{"svg":false,"png":true}},"bancsabadell":{"icon":{"svg":false,"png":true},"logo":{"svg":false,"png":true}},"ssk":{"icon":{"svg":false,"png":true},"logo":{"svg":false,"png":true}},"zapp":{"icon":{"svg":false,"png":true},"logo":{"svg":false,"png":true}},"inghomepay":{"icon":{"svg":false,"png":true},"logo":{"svg":false,"png":true}},"247billpay":{"icon":{"svg":false,"png":true},"logo":{"svg":false,"png":true}},"epese":{"icon":{"svg":false,"png":true}},"privatbank":{"icon":{"svg":false,"png":true},"logo":{"svg":false,"png":true}},"girocard":{"icon":{"svg":false,"png":true},"logo":{"svg":false,"png":true}},"vmevisa":{"icon":{"svg":false,"png":true},"logo":{"svg":false,"png":true}},"neosurf":{"icon":{"svg":false,"png":true},"logo":{"svg":false,"png":true}},"bancnetdirectdebits":{"icon":{"svg":false,"png":true},"logo":{"svg":false,"png":true}},"frenchonlinepaymentmethodewalletpaylib":{"icon":{"svg":false,"png":true},"logo":{"svg":false,"png":true}},"promsvyazbank":{"icon":{"svg":false,"png":true},"logo":{"svg":false,"png":true}},"inpay":{"icon":{"svg":false,"png":true},"logo":{"svg":false,"png":true}},"moneytopay":{"icon":{"svg":false,"png":true},"logo":{"svg":false,"png":true}},"raiffeisenbank":{"icon":{"svg":false,"png":true},"logo":{"svg":false,"png":true}},"walletone":{"icon":{"svg":false,"png":true}},"ssk_md":{"icon":{"svg":false,"png":true},"logo":{"svg":false,"png":true}},"bancopopular":{"icon":{"svg":false,"png":true},"logo":{"svg":false,"png":true}},"hipercard":{"icon":{"svg":false,"png":true},"logo":{"svg":false,"png":true}},"tapiola":{"icon":{"svg":false,"png":true},"logo":{"svg":false,"png":true}},"cifrograd":{"icon":{"svg":false,"png":true},"logo":{"svg":false,"png":true}},"pagorapido":{"icon":{"svg":false,"png":true},"logo":{"svg":false,"png":true}},"danskebank":{"icon":{"svg":false,"png":true},"logo":{"svg":false,"png":true}},"gcashwallet":{"icon":{"svg":false,"png":true},"logo":{"svg":false,"png":true}},"interkassa":{"icon":{"svg":false,"png":true}},"thaimilitarybanktmbnetbanking":{"icon":{"svg":false,"png":true},"logo":{"svg":false,"png":true}},"okpay":{"icon":{"svg":false,"png":true},"logo":{"svg":false,"png":true}},"googlewallet":{"icon":{"svg":false,"png":true},"logo":{"svg":false,"png":true}},"tescolotus":{"icon":{"svg":false,"png":true},"logo":{"svg":false,"png":true}},"liqpay_wallet":{"icon":{"svg":false,"png":true},"logo":{"svg":true,"png":false}},"clickandbuy":{"icon":{"svg":false,"png":true},"logo":{"svg":false,"png":true}},"privat24":{"icon":{"svg":false,"png":true},"logo":{"svg":false,"png":true}},"ukash":{"icon":{"svg":false,"png":true},"logo":{"svg":false,"png":true}},"privatbank_terminals":{"icon":{"svg":false,"png":true},"logo":{"svg":false,"png":true}},"maestro":{"icon":{"svg":false,"png":true},"logo":{"svg":false,"png":true}},"ssk_kz":{"icon":{"svg":false,"png":true},"logo":{"svg":false,"png":true}},"afterpay":{"icon":{"svg":false,"png":true},"logo":{"svg":false,"png":true}},"electroniccheckach":{"icon":{"svg":false,"png":true},"logo":{"svg":false,"png":true}},"account2account":{"icon":{"svg":false,"png":true},"logo":{"svg":false,"png":true}},"yota":{"icon":{"svg":false,"png":true},"logo":{"svg":false,"png":true}},"multibank":{"icon":{"svg":false,"png":true},"logo":{"svg":false,"png":true}},"vpay":{"icon":{"svg":false,"png":true},"logo":{"svg":false,"png":true}},"sebbank":{"icon":{"svg":false,"png":true},"logo":{"svg":false,"png":true}},"mypaywizard":{"icon":{"svg":false,"png":true},"logo":{"svg":false,"png":true}},"qiwi":{"icon":{"svg":false,"png":true},"logo":{"svg":false,"png":true}},"tenpay":{"icon":{"svg":false,"png":true},"logo":{"svg":false,"png":true}},"banktransfer":{"logo":{"svg":true,"png":true},"icon":{"svg":true,"png":false}},"ssk_za":{"icon":{"svg":false,"png":true},"logo":{"svg":false,"png":true}},"libertybank":{"icon":{"svg":false,"png":true},"logo":{"svg":false,"png":true}},"ekonto":{"icon":{"svg":false,"png":true},"logo":{"svg":false,"png":true}},"instantcredit":{"icon":{"svg":false,"png":true},"logo":{"svg":false,"png":true}},"mpayaisthailand":{"icon":{"svg":false,"png":true},"logo":{"svg":false,"png":true}},"billpay":{"icon":{"svg":false,"png":true},"logo":{"svg":false,"png":true}},"elektronischeslastschriftverfahren":{"icon":{"svg":false,"png":true},"logo":{"svg":false,"png":true}},"flexepinemoneyvouchers":{"icon":{"svg":false,"png":true},"logo":{"svg":false,"png":true}},"enetsdirectdebit":{"icon":{"svg":false,"png":true},"logo":{"svg":false,"png":true}},"perfectmoney_account":{"logo":{"svg":true,"png":false},"icon":{"svg":true,"png":false}},"americanexpress":{"icon":{"svg":false,"png":true},"logo":{"svg":false,"png":true}},"cellularworld":{"icon":{"svg":false,"png":true}},"visaelectron":{"icon":{"svg":false,"png":true},"logo":{"svg":false,"png":true}},"erip":{"icon":{"svg":false,"png":true}},"barpay":{"icon":{"svg":false,"png":true},"logo":{"svg":false,"png":true}},"famsaalternativecashpaymentmethodsmexico":{"icon":{"svg":false,"png":true},"logo":{"svg":false,"png":true}},"krungthaibanknetbanking":{"icon":{"svg":false,"png":true},"logo":{"svg":false,"png":true}},"kasikornbankkbanknetbanking":{"icon":{"svg":false,"png":true},"logo":{"svg":false,"png":true}},"pagoefectivo":{"icon":{"svg":false,"png":true},"logo":{"svg":false,"png":true}},"payd":{"icon":{"svg":false,"png":true},"logo":{"svg":false,"png":true}},"postovabanka":{"icon":{"svg":false,"png":true},"logo":{"svg":false,"png":true}},"tarjetanaranjacreditcard":{"icon":{"svg":false,"png":true},"logo":{"svg":false,"png":true}},"carrierbilling":{"icon":{"svg":false,"png":true},"logo":{"svg":false,"png":true}},"poppankki":{"icon":{"svg":false,"png":true},"logo":{"svg":false,"png":true}},"Self service kiosk Russia":{"icon":{"svg":false,"png":true},"logo":{"svg":false,"png":true}},"milleniumbank":{"icon":{"svg":false,"png":true},"logo":{"svg":false,"png":true}},"safetypay":{"icon":{"svg":false,"png":true},"logo":{"svg":false,"png":true}},"rbkmoney":{"icon":{"svg":false,"png":true}},"viber":{"icon":{"svg":false,"png":true},"logo":{"svg":false,"png":true}},"banamexdebitcardonlinepaymentmethodmexico":{"icon":{"svg":false,"png":true},"logo":{"svg":false,"png":true}},"kriita2":{"icon":{"svg":false,"png":true},"logo":{"svg":false,"png":true}},"pagofacil":{"icon":{"svg":false,"png":true},"logo":{"svg":false,"png":true}},"visa2":{"icon":{"svg":false,"png":true},"logo":{"svg":false,"png":true}},"nsmep":{"icon":{"svg":false,"png":true}},"payeer":{"icon":{"svg":false,"png":true},"logo":{"svg":false,"png":true}},"ibox":{"icon":{"svg":false,"png":true}},"postfinancecard":{"icon":{"svg":false,"png":true},"logo":{"svg":false,"png":true}},"banklink":{"icon":{"svg":false,"png":true},"logo":{"svg":false,"png":true}},"liqpay":{"icon":{"svg":true,"png":true},"logo":{"svg":true,"png":false}},"ideal":{"icon":{"svg":false,"png":true},"logo":{"svg":false,"png":true}},"ingpl":{"logo":{"svg":true,"png":false},"icon":{"svg":true,"png":false}},"vubbanka":{"icon":{"svg":false,"png":true},"logo":{"svg":false,"png":true}},"test":{"icon":{"svg":true,"png":true},"logo":{"svg":false,"png":true}},"billsafe":{"icon":{"svg":false,"png":true},"logo":{"svg":false,"png":true}},"jcb":{"icon":{"svg":false,"png":true},"logo":{"svg":false,"png":true}},"rapipago":{"icon":{"svg":false,"png":true},"logo":{"svg":false,"png":true}},"cabal":{"icon":{"svg":false,"png":true},"logo":{"svg":false,"png":true}},"serve":{"icon":{"svg":false,"png":true},"logo":{"svg":false,"png":true}},"achdebits":{"icon":{"svg":false,"png":true},"logo":{"svg":false,"png":true}},"Self service kiosk Ukraine":{"icon":{"svg":false,"png":true},"logo":{"svg":false,"png":true}},"csob":{"icon":{"svg":false,"png":true},"logo":{"svg":false,"png":true}},"komercnibanka":{"icon":{"svg":false,"png":true},"logo":{"svg":false,"png":true}},"bankzachodniwbk":{"icon":{"svg":false,"png":true},"logo":{"svg":false,"png":true}},"usemyservices":{"icon":{"svg":false,"png":true},"logo":{"svg":false,"png":true}},"ivrbilling":{"icon":{"svg":false,"png":true},"logo":{"svg":false,"png":true}},"acceptgiro":{"icon":{"svg":false,"png":true},"logo":{"svg":false,"png":true}},"postepay":{"icon":{"svg":false,"png":true},"logo":{"svg":false,"png":true}},"coingate":{"icon":{"svg":false,"png":true},"logo":{"svg":true,"png":false}},"pingping":{"icon":{"svg":false,"png":true},"logo":{"svg":false,"png":true}},"futurepay":{"icon":{"svg":false,"png":true},"logo":{"svg":false,"png":true}},"bankia":{"icon":{"svg":false,"png":true},"logo":{"svg":false,"png":true}},"billink":{"icon":{"svg":false,"png":true},"logo":{"svg":false,"png":true}},"bankaxess":{"icon":{"svg":false,"png":true},"logo":{"svg":false,"png":true}},"russianpost":{"icon":{"svg":false,"png":true},"logo":{"svg":false,"png":true}},"krungsrinetbanking":{"icon":{"svg":false,"png":true},"logo":{"svg":false,"png":true}},"rixty":{"icon":{"svg":false,"png":true},"logo":{"svg":false,"png":true}},"viabill":{"icon":{"svg":false,"png":true},"logo":{"svg":false,"png":true}},"billmelater":{"icon":{"svg":false,"png":true},"logo":{"svg":false,"png":true}},"perfectmoney_voucher":{"icon":{"svg":false,"png":true},"logo":{"svg":false,"png":true}},"paysafecard":{"icon":{"svg":false,"png":true},"logo":{"svg":false,"png":true}},"paydirektalternativepaymentmethodgermany":{"icon":{"svg":false,"png":true},"logo":{"svg":false,"png":true}},"bangkokbanknetbanking":{"icon":{"svg":false,"png":true},"logo":{"svg":false,"png":true}},"bpay":{"icon":{"svg":false,"png":true},"logo":{"svg":false,"png":true}},"bank_card":{"icon":{"svg":true,"png":false}},"masterpass":{"icon":{"svg":false,"png":true},"logo":{"svg":false,"png":true}},"otpbank":{"icon":{"svg":false,"png":true},"logo":{"svg":false,"png":true}},"kievstar":{"icon":{"svg":false,"png":true},"logo":{"svg":false,"png":true}},"tinkoff":{"icon":{"svg":false,"png":true},"logo":{"svg":false,"png":true}},"ssk_ge":{"icon":{"svg":false,"png":true},"logo":{"svg":false,"png":true}},"debitobradesco":{"icon":{"svg":false,"png":true},"logo":{"svg":false,"png":true}},"bitcoins":{"icon":{"svg":false,"png":true},"logo":{"svg":false,"png":true}},"usdt":{"icon":{"svg":false,"png":true},"logo":{"svg":false,"png":true}},"erstebank":{"icon":{"svg":false,"png":true},"logo":{"svg":false,"png":true}},"barzahlen":{"icon":{"svg":false,"png":true},"logo":{"svg":false,"png":true}},"wupay":{"icon":{"svg":false,"png":true},"logo":{"svg":false,"png":true}},"cartasi":{"icon":{"svg":false,"png":true},"logo":{"svg":false,"png":true}},"svyaznoy":{"icon":{"svg":false,"png":true}},"paysbuy":{"icon":{"svg":false,"png":true},"logo":{"svg":false,"png":true}},"mazooma":{"icon":{"svg":false,"png":true},"logo":{"svg":false,"png":true}},"webmoneytransfer":{"icon":{"svg":false,"png":true},"logo":{"svg":false,"png":true}},"sofortbanking":{"icon":{"svg":false,"png":true},"logo":{"svg":false,"png":true}},"zimpler":{"icon":{"svg":false,"png":true},"logo":{"svg":false,"png":true}},"bancopastor":{"icon":{"svg":false,"png":true},"logo":{"svg":false,"png":true}},"visadebit":{"icon":{"svg":false,"png":true},"logo":{"svg":false,"png":true}},"elo":{"icon":{"svg":false,"png":true},"logo":{"svg":false,"png":true}},"advcash":{"icon":{"svg":false,"png":true},"logo":{"svg":false,"png":true}},"fakturaru":{"icon":{"svg":false,"png":true}},"swedbank":{"icon":{"svg":false,"png":true},"logo":{"svg":false,"png":true}},"yandexmoney":{"icon":{"svg":false,"png":true},"logo":{"svg":false,"png":true}},"ssk_ru":{"icon":{"svg":false,"png":true},"logo":{"svg":false,"png":true}},"skandiabanken":{"icon":{"svg":false,"png":true},"logo":{"svg":false,"png":true}},"mts":{"icon":{"svg":false,"png":true},"logo":{"svg":false,"png":true}},"bkmexpress":{"icon":{"svg":false,"png":true},"logo":{"svg":false,"png":true}},"magnacreditcardsonlinepaymentmethodschile":{"icon":{"svg":false,"png":true},"logo":{"svg":false,"png":true}},"exmo":{"icon":{"svg":false,"png":true},"logo":{"svg":false,"png":true}},"psbretail":{"icon":{"svg":false,"png":true}},"ukrsibbank":{"icon":{"svg":false,"png":true},"logo":{"svg":false,"png":true}},"bankofchinanetbanking":{"icon":{"svg":false,"png":true},"logo":{"svg":false,"png":true}},"pravexbank":{"icon":{"svg":false,"png":true},"logo":{"svg":false,"png":true}},"ssk_by":{"icon":{"svg":false,"png":true},"logo":{"svg":false,"png":true}},"icicinetbanking":{"icon":{"svg":false,"png":true},"logo":{"svg":false,"png":true}},"mastercard":{"icon":{"svg":false,"png":true},"logo":{"svg":false,"png":true}},"saastopankki":{"icon":{"svg":false,"png":true},"logo":{"svg":false,"png":true}},"minitix":{"icon":{"svg":false,"png":true},"logo":{"svg":false,"png":true}},"tele2ru":{"icon":{"svg":false,"png":true},"logo":{"svg":false,"png":true}},"euteller":{"icon":{"svg":false,"png":true},"logo":{"svg":false,"png":true}},"kbcbetaalknop":{"icon":{"svg":false,"png":true},"logo":{"svg":false,"png":true}},"papercheck":{"icon":{"svg":false,"png":true},"logo":{"svg":false,"png":true}},"interac":{"icon":{"svg":false,"png":true},"logo":{"svg":false,"png":true}},"webpaypluscreditcardsonlinepaymentsolutionchile":{"icon":{"svg":false,"png":true},"logo":{"svg":false,"png":true}},"paymer":{"icon":{"svg":false,"png":true},"logo":{"svg":false,"png":true}},"dwolla":{"icon":{"svg":false,"png":true},"logo":{"svg":false,"png":true}},"lansforsakringar":{"icon":{"svg":false,"png":true},"logo":{"svg":false,"png":true}},"asdasda":{"logo":{"svg":true,"png":true}},"Self service kiosk Belarus":{"icon":{"svg":false,"png":true},"logo":{"svg":false,"png":true}},"unicredit":{"icon":{"svg":false,"png":true},"logo":{"svg":false,"png":true}},"efectyonlinecashpaymentmethodscolombia":{"icon":{"svg":false,"png":true},"logo":{"svg":false,"png":true}},"maybanknetbankingphillipines":{"icon":{"svg":false,"png":true},"logo":{"svg":false,"png":true}},"cimbclicksinternetbanking":{"icon":{"svg":false,"png":true},"logo":{"svg":false,"png":true}},"justpayewallet":{"icon":{"svg":false,"png":true},"logo":{"svg":false,"png":true}},"lider":{"icon":{"svg":false,"png":true},"logo":{"svg":false,"png":true}},"cartebleue":{"icon":{"svg":false,"png":true},"logo":{"svg":false,"png":true}},"mercadopago":{"icon":{"svg":false,"png":true},"logo":{"svg":false,"png":true}},"slovenskasporitelna":{"icon":{"svg":false,"png":true},"logo":{"svg":false,"png":true}},"toditocash":{"icon":{"svg":false,"png":true},"logo":{"svg":false,"png":true}},"ssk_ua":{"icon":{"svg":false,"png":true}},"forexbank":{"icon":{"svg":false,"png":true},"logo":{"svg":false,"png":true}},"fastcheckoutmultisafepay":{"icon":{"svg":false,"png":true},"logo":{"svg":false,"png":true}},"sbrebank":{"icon":{"svg":false,"png":true},"logo":{"svg":false,"png":true}},"farmaciasdelahorroalternativecashpaymentmethodsmexico":{"icon":{"svg":false,"png":true},"logo":{"svg":false,"png":true}},"wiretransfer":{"icon":{"svg":false,"png":true},"logo":{"svg":false,"png":true}},"primabanka":{"icon":{"svg":false,"png":true},"logo":{"svg":false,"png":true}},"oppohjola":{"icon":{"svg":false,"png":true},"logo":{"svg":false,"png":true}},"postpay":{"icon":{"svg":false,"png":true},"logo":{"svg":false,"png":true}},"payzippy":{"icon":{"svg":false,"png":true},"logo":{"svg":false,"png":true}},"mybank2":{"icon":{"svg":false,"png":true},"logo":{"svg":false,"png":true}},"tarjetaripley":{"icon":{"svg":false,"png":true},"logo":{"svg":false,"png":true}},"gemoney":{"icon":{"svg":false,"png":true},"logo":{"svg":false,"png":true}},"przelewy24":{"icon":{"svg":false,"png":true},"logo":{"svg":false,"png":true}},"unistream":{"icon":{"svg":false,"png":true},"logo":{"svg":false,"png":true}},"aura":{"icon":{"svg":false,"png":true},"logo":{"svg":false,"png":true}},"Self service kiosk South Africa":{"icon":{"svg":false,"png":true},"logo":{"svg":false,"png":true}},"klarna":{"icon":{"svg":false,"png":true},"logo":{"svg":false,"png":true}},"uatp":{"icon":{"svg":false,"png":true},"logo":{"svg":false,"png":true}},"viabalotoonlinecashpaymentmethodscolombia":{"icon":{"svg":false,"png":true},"logo":{"svg":false,"png":true}},"kwixo":{"icon":{"svg":false,"png":true},"logo":{"svg":false,"png":true}},"farmaciasbenavidesalternativecashpaymentmethodsmexico":{"icon":{"svg":false,"png":true},"logo":{"svg":false,"png":true}},"discover":{"icon":{"svg":false,"png":true},"logo":{"svg":false,"png":true}},"mminvoicing":{"icon":{"svg":false,"png":true}},"bancobrasil":{"icon":{"svg":false,"png":true},"logo":{"svg":false,"png":true}},"smartmoney":{"icon":{"svg":false,"png":true},"logo":{"svg":false,"png":true}},"perfectmoney":{"logo":{"svg":false,"png":true}},"epayua":{"icon":{"svg":false,"png":true},"logo":{"svg":false,"png":true}},"ciberpay":{"icon":{"svg":false,"png":true},"logo":{"svg":false,"png":true}},"card":{"icon":{"svg":true,"png":true},"logo":{"svg":true,"png":false}},"vvvgiftcard":{"icon":{"svg":false,"png":true},"logo":{"svg":false,"png":true}},"ticketpremium":{"icon":{"svg":false,"png":true},"logo":{"svg":false,"png":true}},"qazkombank":{"icon":{"svg":false,"png":true},"logo":{"svg":false,"png":true}},"bigconlinepayment":{"icon":{"svg":false,"png":true},"logo":{"svg":false,"png":true}},"teleingreso":{"icon":{"svg":false,"png":true},"logo":{"svg":false,"png":true}},"7elevenalternativecashpaymentmethodsmexico":{"icon":{"svg":false,"png":true},"logo":{"svg":false,"png":true}},"multibanconet":{"icon":{"svg":false,"png":true},"logo":{"svg":false,"png":true}},"cash":{"icon":{"svg":false,"png":true}},"scbbanknetbanking":{"icon":{"svg":false,"png":true},"logo":{"svg":false,"png":true}},"moneta":{"icon":{"svg":false,"png":true},"logo":{"svg":false,"png":true}},"onlinenaira":{"icon":{"svg":false,"png":true},"logo":{"svg":false,"png":true}},"ecoineu":{"icon":{"svg":false,"png":true}},"jyskebank":{"icon":{"svg":false,"png":true},"logo":{"svg":false,"png":true}},"payfastwallet":{"icon":{"svg":false,"png":true},"logo":{"svg":false,"png":true}},"sepadirectdebit":{"icon":{"svg":false,"png":true},"logo":{"svg":false,"png":true}},"cashu":{"icon":{"svg":false,"png":true},"logo":{"svg":false,"png":true}},"dinersclub":{"icon":{"svg":false,"png":true},"logo":{"svg":false,"png":true}},"easypay":{"icon":{"svg":false,"png":true},"logo":{"svg":false,"png":true}},"servipag":{"icon":{"svg":false,"png":true},"logo":{"svg":false,"png":true}},"bancodobrasilcomercioeletronico":{"icon":{"svg":false,"png":true},"logo":{"svg":false,"png":true}},"eps":{"icon":{"svg":false,"png":true},"logo":{"svg":false,"png":true}},"peela":{"icon":{"svg":false,"png":true},"logo":{"svg":false,"png":true}},"Self service kiosk Moldova":{"icon":{"svg":false,"png":true},"logo":{"svg":false,"png":true}},"volksbank":{"icon":{"svg":false,"png":true},"logo":{"svg":false,"png":true}},"mastercarddebit":{"icon":{"svg":false,"png":true},"logo":{"svg":false,"png":true}},"polipayonline":{"icon":{"svg":false,"png":true},"logo":{"svg":false,"png":true}},"mobikwik":{"icon":{"svg":false,"png":true},"logo":{"svg":false,"png":true}},"vtb24":{"icon":{"svg":false,"png":true},"logo":{"svg":false,"png":true}},"russian_standart_bank":{"icon":{"svg":false,"png":true},"logo":{"svg":false,"png":true}},"santander":{"icon":{"svg":false,"png":true},"logo":{"svg":false,"png":true}},"tas24":{"icon":{"svg":false,"png":true}},"zipmark":{"icon":{"svg":false,"png":true},"logo":{"svg":false,"png":true}},"pagseguro":{"icon":{"svg":false,"png":true},"logo":{"svg":false,"png":true}},"paynearme":{"icon":{"svg":false,"png":true},"logo":{"svg":false,"png":true}},"redcompraalternativeonlinepaymentmethodchile":{"icon":{"svg":false,"png":true},"logo":{"svg":false,"png":true}},"bitcoin_cash":{"icon":{"svg":false,"png":true},"logo":{"svg":false,"png":true}},"oxxoalternativecashpaymentmethodsmexico":{"icon":{"svg":false,"png":true},"logo":{"svg":false,"png":true}},"boletobancariopay":{"icon":{"svg":false,"png":true},"logo":{"svg":false,"png":true}},"rupaypaysecure":{"icon":{"svg":false,"png":true},"logo":{"svg":false,"png":true}},"ceskasporitelna":{"icon":{"svg":false,"png":true},"logo":{"svg":false,"png":true}},"unitedoverseasbankuobnetbanking":{"icon":{"svg":false,"png":true},"logo":{"svg":false,"png":true}},"wmcard":{"icon":{"svg":false,"png":true},"logo":{"svg":false,"png":true}},"bdooverthecounterofflinebankdeposit":{"icon":{"svg":false,"png":true},"logo":{"svg":false,"png":true}},"provinciapagos":{"icon":{"svg":false,"png":true},"logo":{"svg":false,"png":true}},"ethereum":{"icon":{"svg":false,"png":true},"logo":{"svg":false,"png":true}},"wmnote":{"icon":{"svg":false,"png":true},"logo":{"svg":false,"png":true}},"ssk_tj":{"icon":{"svg":false,"png":true},"logo":{"svg":false,"png":true}},"osuuspankki":{"icon":{"svg":false,"png":true},"logo":{"svg":false,"png":true}},"lacaixa":{"icon":{"svg":false,"png":true},"logo":{"svg":false,"png":true}},"bancoitau":{"icon":{"svg":false,"png":true},"logo":{"svg":false,"png":true}},"icabanken":{"icon":{"svg":false,"png":true},"logo":{"svg":false,"png":true}},"creditagricole":{"icon":{"svg":false,"png":true},"logo":{"svg":false,"png":true}},"presto":{"icon":{"svg":false,"png":true},"logo":{"svg":false,"png":true}},"aktia":{"icon":{"svg":false,"png":true},"logo":{"svg":false,"png":true}}}