{"euteller":{"logo":{"svg":false,"png":true},"icon":{"svg":false,"png":true}},"bitcoin":{"logo":{"svg":true,"png":false},"icon":{"svg":true,"png":false}},"payfastwallet":{"logo":{"svg":false,"png":true},"icon":{"svg":false,"png":true}},"sencillito":{"logo":{"svg":true,"png":false},"icon":{"svg":true,"png":false}},"pix_crypto":{"logo":{"svg":true,"png":false},"icon":{"svg":true,"png":false}},"bri_bank":{"logo":{"svg":true,"png":false},"icon":{"svg":true,"png":false}},"momo":{"logo":{"svg":false,"png":true},"icon":{"svg":false,"png":true}},"westpac":{"logo":{"svg":true,"png":false},"icon":{"svg":true,"png":false}},"paysense":{"logo":{"svg":true,"png":false},"icon":{"svg":true,"png":false}},"kotak_mahindra_bank":{"logo":{"svg":false,"png":true},"icon":{"svg":false,"png":true}},"pagorapido":{"logo":{"svg":false,"png":true},"icon":{"svg":false,"png":true}},"china_union_pay":{"logo":{"svg":true,"png":false},"icon":{"svg":true,"png":false}},"bitcoin_cash":{"logo":{"svg":false,"png":true},"icon":{"svg":false,"png":true}},"canara_bank":{"logo":{"svg":true,"png":false},"icon":{"svg":true,"png":false}},"lider":{"logo":{"svg":false,"png":true},"icon":{"svg":false,"png":true}},"uax":{"logo":{"svg":true,"png":false},"icon":{"svg":true,"png":false}},"carrierbilling":{"logo":{"svg":false,"png":true},"icon":{"svg":false,"png":true}},"electroniccheckach":{"logo":{"svg":false,"png":true},"icon":{"svg":false,"png":true}},"mminvoicing":{"logo":{"svg":false,"png":true},"icon":{"svg":false,"png":true}},"zimpler":{"logo":{"svg":false,"png":true},"icon":{"svg":false,"png":true}},"unibank_kommersiya_banki_leobank":{"logo":{"svg":false,"png":true},"icon":{"svg":false,"png":true}},"snsbank":{"logo":{"svg":false,"png":true},"icon":{"svg":false,"png":true}},"cepbank":{"logo":{"svg":false,"png":true},"icon":{"svg":false,"png":true}},"visa":{"logo":{"svg":true,"png":false},"icon":{"svg":true,"png":false}},"kunapay_crypto":{"icon":{"svg":false,"png":true},"logo":{"svg":true,"png":false}},"calimax_cash":{"logo":{"svg":false,"png":true},"icon":{"svg":false,"png":true}},"ssk_za":{"logo":{"svg":false,"png":true},"icon":{"svg":false,"png":true}},"futurepay":{"logo":{"svg":false,"png":true},"icon":{"svg":false,"png":true}},"gemoney":{"logo":{"svg":false,"png":true},"icon":{"svg":false,"png":true}},"advcash_card":{"logo":{"svg":true,"png":false},"icon":{"svg":true,"png":false}},"andhra_bank":{"logo":{"svg":true,"png":false},"icon":{"svg":true,"png":false}},"bdo":{"logo":{"svg":true,"png":false},"icon":{"svg":true,"png":false}},"btn_bank":{"logo":{"svg":false,"png":true},"icon":{"svg":false,"png":true}},"krungsri":{"logo":{"svg":false,"png":true},"icon":{"svg":false,"png":true}},"twint":{"logo":{"svg":true,"png":false},"icon":{"svg":true,"png":false}},"industrial_bank_ho_chi_minh":{"logo":{"svg":false,"png":true},"icon":{"svg":false,"png":true}},"soriana_cash":{"logo":{"svg":false,"png":true},"icon":{"svg":false,"png":true}},"saigon_bank":{"logo":{"svg":false,"png":true},"icon":{"svg":false,"png":true}},"khalti":{"logo":{"svg":true,"png":false},"icon":{"svg":true,"png":false}},"visa2":{"logo":{"svg":false,"png":true},"icon":{"svg":false,"png":true}},"free_money":{"logo":{"svg":true,"png":false},"icon":{"svg":true,"png":false}},"pvcom_bank":{"logo":{"svg":false,"png":true},"icon":{"svg":false,"png":true}},"geopaynet_transfer":{"logo":{"svg":true,"png":false},"icon":{"svg":true,"png":false}},"piastrix":{"logo":{"svg":true,"png":false},"icon":{"svg":true,"png":false}},"farmaciasbenavidesalternativecashpaymentmethodsmexico":{"logo":{"svg":false,"png":true},"icon":{"svg":false,"png":true}},"ssk_ru":{"logo":{"svg":false,"png":true},"icon":{"svg":false,"png":true}},"maharashtra_bank_india":{"logo":{"svg":true,"png":false},"icon":{"svg":true,"png":false}},"justpayewallet":{"logo":{"svg":false,"png":true},"icon":{"svg":false,"png":true}},"liqpay_wallet":{"logo":{"svg":true,"png":false},"icon":{"svg":true,"png":false}},"ukash":{"logo":{"svg":false,"png":true},"icon":{"svg":false,"png":true}},"bodega_aurrera":{"logo":{"svg":true,"png":false},"icon":{"svg":true,"png":false}},"pay_id_crypto":{"logo":{"svg":true,"png":false},"icon":{"svg":true,"png":false}},"western_union_panama_cash":{"logo":{"svg":false,"png":true},"icon":{"svg":false,"png":true}},"zipmark":{"logo":{"svg":false,"png":true},"icon":{"svg":false,"png":true}},"volksbank":{"logo":{"svg":false,"png":true},"icon":{"svg":false,"png":true}},"milleniumbank":{"logo":{"svg":false,"png":true},"icon":{"svg":false,"png":true}},"solana":{"logo":{"svg":true,"png":false},"icon":{"svg":true,"png":false}},"paypay":{"logo":{"svg":false,"png":true},"icon":{"svg":false,"png":true}},"swift":{"logo":{"svg":true,"png":false},"icon":{"svg":true,"png":false}},"mach":{"logo":{"svg":false,"png":true},"icon":{"svg":false,"png":true}},"ekonto":{"logo":{"svg":false,"png":true},"icon":{"svg":false,"png":true}},"interac":{"logo":{"svg":false,"png":true},"icon":{"svg":false,"png":true}},"kien_long_bank":{"logo":{"svg":false,"png":true},"icon":{"svg":false,"png":true}},"ned_bank":{"logo":{"svg":false,"png":true},"icon":{"svg":false,"png":true}},"vijaya_bank":{"logo":{"svg":true,"png":false},"icon":{"svg":true,"png":false}},"viet_capital_bank":{"logo":{"svg":false,"png":true},"icon":{"svg":false,"png":true}},"tarjetaripley":{"logo":{"svg":false,"png":true},"icon":{"svg":false,"png":true}},"paynearme":{"logo":{"svg":false,"png":true},"icon":{"svg":false,"png":true}},"cartebleue":{"logo":{"svg":false,"png":true},"icon":{"svg":false,"png":true}},"astropayunion":{"logo":{"svg":true,"png":false},"icon":{"svg":true,"png":false}},"skandiabanken":{"logo":{"svg":false,"png":true},"icon":{"svg":false,"png":true}},"bancsabadell":{"logo":{"svg":false,"png":true},"icon":{"svg":false,"png":true}},"banco_guayaquil":{"logo":{"svg":false,"png":true},"icon":{"svg":false,"png":true}},"privatbank":{"logo":{"svg":true,"png":false},"icon":{"svg":true,"png":false}},"payu":{"logo":{"svg":false,"png":true},"icon":{"svg":false,"png":true}},"bank_of_communication":{"logo":{"svg":true,"png":false},"icon":{"svg":true,"png":false}},"ab_bank":{"logo":{"svg":false,"png":true},"icon":{"svg":false,"png":true}},"loteria":{"logo":{"svg":false,"png":true},"icon":{"svg":false,"png":true}},"mir":{"logo":{"svg":true,"png":false},"icon":{"svg":true,"png":false}},"china_citic_bank":{"logo":{"svg":true,"png":false},"icon":{"svg":true,"png":false}},"boost":{"logo":{"svg":true,"png":false},"icon":{"svg":true,"png":false}},"paybybill":{"logo":{"svg":false,"png":true},"icon":{"svg":false,"png":true}},"cps":{"logo":{"svg":false,"png":true},"icon":{"svg":false,"png":true}},"danamon_bank":{"logo":{"svg":false,"png":true},"icon":{"svg":false,"png":true}},"n26_bank":{"logo":{"svg":false,"png":true},"icon":{"svg":false,"png":true}},"multibank":{"logo":{"svg":false,"png":true},"icon":{"svg":false,"png":true}},"credit_mutuel_bank":{"logo":{"svg":false,"png":true},"icon":{"svg":false,"png":true}},"postovabanka":{"logo":{"svg":false,"png":true},"icon":{"svg":false,"png":true}},"acceptgiro":{"logo":{"svg":false,"png":true},"icon":{"svg":false,"png":true}},"curfex":{"logo":{"svg":false,"png":true},"icon":{"svg":false,"png":true}},"unionpay_qr":{"logo":{"svg":true,"png":false},"icon":{"svg":true,"png":false}},"creditcard":{"icon":{"svg":true,"png":true},"logo":{"svg":true,"png":false}},"banco_pichincha":{"logo":{"svg":false,"png":true},"icon":{"svg":false,"png":true}},"mb_way":{"logo":{"svg":true,"png":false},"icon":{"svg":true,"png":false}},"servipag":{"logo":{"svg":false,"png":true},"icon":{"svg":false,"png":true}},"deutsche_bank_india":{"logo":{"svg":false,"png":true},"icon":{"svg":false,"png":true}},"webpaypluscreditcardsonlinepaymentsolutionchile":{"logo":{"svg":false,"png":true},"icon":{"svg":false,"png":true}},"dwolla":{"logo":{"svg":true,"png":false},"icon":{"svg":true,"png":false}},"sams_club":{"logo":{"svg":false,"png":true},"icon":{"svg":false,"png":true}},"oriental_bank_of_commerce":{"logo":{"svg":false,"png":true},"icon":{"svg":true,"png":false}},"visaelectron":{"logo":{"svg":false,"png":true},"icon":{"svg":false,"png":true}},"ssk_tj":{"logo":{"svg":false,"png":true},"icon":{"svg":false,"png":true}},"mpayaisthailand":{"logo":{"svg":false,"png":true},"icon":{"svg":false,"png":true}},"hipercard":{"logo":{"svg":false,"png":true},"icon":{"svg":false,"png":true}},"halo_pesa":{"logo":{"svg":false,"png":true},"icon":{"svg":false,"png":true}},"ripley_cash":{"logo":{"svg":false,"png":true},"icon":{"svg":false,"png":true}},"astropaydirect":{"logo":{"svg":true,"png":false},"icon":{"svg":true,"png":false}},"opay":{"logo":{"svg":true,"png":false},"icon":{"svg":true,"png":false}},"lansforsakringar":{"logo":{"svg":false,"png":true},"icon":{"svg":false,"png":true}},"standard_bank":{"logo":{"svg":false,"png":true},"icon":{"svg":false,"png":true}},"icbc":{"logo":{"svg":false,"png":true},"icon":{"svg":false,"png":true}},"sepa_transfer_instant":{"logo":{"svg":true,"png":false},"icon":{"svg":true,"png":false}},"lider_cash":{"logo":{"svg":false,"png":true},"icon":{"svg":false,"png":true}},"mercadopago":{"logo":{"svg":false,"png":true},"icon":{"svg":false,"png":true}},"tigo_pesa":{"logo":{"svg":false,"png":true},"icon":{"svg":false,"png":true}},"hana_bank":{"logo":{"svg":false,"png":true},"icon":{"svg":false,"png":true}},"onlinenaira":{"logo":{"svg":false,"png":true},"icon":{"svg":false,"png":true}},"spcbl":{"logo":{"svg":false,"png":true},"icon":{"svg":false,"png":true}},"farmaciasbenavides":{"logo":{"svg":true,"png":false},"icon":{"svg":true,"png":false}},"billpay":{"logo":{"svg":false,"png":true},"icon":{"svg":false,"png":true}},"multibanconet":{"logo":{"svg":false,"png":true},"icon":{"svg":false,"png":true}},"berliner_sparkasse":{"logo":{"svg":false,"png":true},"icon":{"svg":false,"png":true}},"krung_thai_bank":{"logo":{"svg":true,"png":false},"icon":{"svg":true,"png":false}},"easypay":{"logo":{"svg":false,"png":true},"icon":{"svg":false,"png":true}},"caja_arequipa":{"logo":{"svg":false,"png":true},"icon":{"svg":false,"png":true}},"pix_qr":{"logo":{"svg":true,"png":false},"icon":{"svg":true,"png":false}},"paybybank":{"logo":{"svg":false,"png":true},"icon":{"svg":false,"png":true}},"indusind_bank":{"logo":{"svg":false,"png":true},"icon":{"svg":false,"png":true}},"viabill":{"logo":{"svg":false,"png":true},"icon":{"svg":false,"png":true}},"allahabad_bank":{"logo":{"svg":true,"png":false},"icon":{"svg":true,"png":false}},"bnp_paribas_bank":{"logo":{"svg":true,"png":false},"icon":{"svg":true,"png":false}},"spankki":{"logo":{"svg":false,"png":true},"icon":{"svg":false,"png":true}},"bankaxess":{"logo":{"svg":false,"png":true},"icon":{"svg":false,"png":true}},"binance_smart_chain":{"logo":{"svg":false,"png":true},"icon":{"svg":false,"png":true}},"viettelpay":{"logo":{"svg":true,"png":false},"icon":{"svg":true,"png":false}},"gcashwallet":{"logo":{"svg":false,"png":true},"icon":{"svg":false,"png":true}},"lacaixa":{"logo":{"svg":false,"png":true},"icon":{"svg":false,"png":true}},"algorand":{"logo":{"svg":false,"png":true},"icon":{"svg":false,"png":true}},"cellularworld":{"logo":{"svg":false,"png":true},"icon":{"svg":false,"png":true}},"presto":{"logo":{"svg":false,"png":true},"icon":{"svg":false,"png":true}},"caja_trujillo":{"logo":{"svg":false,"png":true},"icon":{"svg":false,"png":true}},"industrial_bank":{"logo":{"svg":true,"png":false},"icon":{"svg":true,"png":false}},"vcreditos":{"logo":{"svg":true,"png":false},"icon":{"svg":true,"png":false}},"supercity":{"logo":{"svg":false,"png":true},"icon":{"svg":false,"png":true}},"siam_commercial_bank":{"logo":{"svg":true,"png":false},"icon":{"svg":true,"png":false}},"ingspain":{"logo":{"svg":false,"png":true},"icon":{"svg":false,"png":true}},"techom_bank":{"logo":{"svg":true,"png":false},"icon":{"svg":true,"png":false}},"astropaymanual":{"logo":{"svg":true,"png":false},"icon":{"svg":true,"png":false}},"national_australia_bank":{"logo":{"svg":true,"png":false},"icon":{"svg":true,"png":false}},"payshop":{"logo":{"svg":false,"png":true},"icon":{"svg":false,"png":true}},"anymoney":{"logo":{"svg":false,"png":true},"icon":{"svg":false,"png":true}},"poppankki":{"logo":{"svg":false,"png":true},"icon":{"svg":false,"png":true}},"kanata_sahakari_bank":{"logo":{"svg":false,"png":true},"icon":{"svg":false,"png":true}},"pravexbank":{"logo":{"svg":false,"png":true},"icon":{"svg":false,"png":true}},"barpay":{"logo":{"svg":false,"png":true},"icon":{"svg":false,"png":true}},"paybis":{"logo":{"svg":false,"png":true},"icon":{"svg":false,"png":true}},"bank_rakyat_indonesia":{"logo":{"svg":true,"png":false},"icon":{"svg":true,"png":false}},"banco_nacion":{"logo":{"svg":false,"png":true},"icon":{"svg":false,"png":true}},"standard_chartered_bank_korea":{"logo":{"svg":true,"png":false},"icon":{"svg":true,"png":false}},"codi":{"logo":{"svg":true,"png":false},"icon":{"svg":true,"png":false}},"international_bank_of_azerbaijan_abb":{"logo":{"svg":false,"png":true},"icon":{"svg":false,"png":true}},"orange_money":{"logo":{"svg":false,"png":true},"icon":{"svg":false,"png":true}},"epese":{"logo":{"svg":false,"png":true},"icon":{"svg":false,"png":true}},"sofort":{"logo":{"svg":true,"png":false},"icon":{"svg":true,"png":false}},"idbi_bank":{"logo":{"svg":true,"png":false},"icon":{"svg":true,"png":false}},"psbretail":{"logo":{"svg":false,"png":true},"icon":{"svg":false,"png":true}},"beeline":{"logo":{"svg":false,"png":true},"icon":{"svg":false,"png":true}},"idfc_bank_india":{"logo":{"svg":true,"png":false},"icon":{"svg":true,"png":false}},"payd":{"logo":{"svg":false,"png":true},"icon":{"svg":false,"png":true}},"may_bank_fpx":{"logo":{"svg":true,"png":false},"icon":{"svg":true,"png":false}},"tp_bank":{"logo":{"svg":false,"png":true},"icon":{"svg":false,"png":true}},"vmevisa":{"logo":{"svg":false,"png":true},"icon":{"svg":false,"png":true}},"bbva_continental_cash":{"logo":{"svg":false,"png":true},"icon":{"svg":false,"png":true}},"moneymail":{"logo":{"svg":false,"png":true},"icon":{"svg":false,"png":true}},"bangko_bank":{"logo":{"svg":true,"png":false},"icon":{"svg":true,"png":false}},"klyme":{"logo":{"svg":false,"png":true},"icon":{"svg":false,"png":true}},"abn_amro_bank":{"logo":{"svg":true,"png":false},"icon":{"svg":true,"png":false}},"bpay":{"logo":{"svg":false,"png":true},"icon":{"svg":false,"png":true}},"euroset":{"logo":{"svg":false,"png":true},"icon":{"svg":false,"png":true}},"pagomovil":{"logo":{"svg":false,"png":true},"icon":{"svg":false,"png":true}},"bbva_bancomer_cash":{"logo":{"svg":false,"png":true},"icon":{"svg":false,"png":true}},"polygon":{"logo":{"svg":true,"png":false},"icon":{"svg":true,"png":false}},"breb":{"logo":{"svg":false,"png":true},"icon":{"svg":false,"png":true}},"picksell":{"logo":{"svg":false,"png":true},"icon":{"svg":false,"png":true}},"wmnote":{"logo":{"svg":false,"png":true},"icon":{"svg":false,"png":true}},"webmoneytransfer":{"logo":{"svg":true,"png":false},"icon":{"svg":true,"png":false}},"polipayonline":{"logo":{"svg":false,"png":true},"icon":{"svg":false,"png":true}},"ukrsibbank":{"logo":{"svg":false,"png":true},"icon":{"svg":false,"png":true}},"neopay":{"logo":{"svg":true,"png":false},"icon":{"svg":true,"png":false}},"smartmoney":{"logo":{"svg":false,"png":true},"icon":{"svg":false,"png":true}},"banco_nacional_cash":{"logo":{"svg":false,"png":true},"icon":{"svg":false,"png":true}},"bbva":{"logo":{"svg":false,"png":true},"icon":{"svg":false,"png":true}},"dhanalaxmi_bank_india":{"logo":{"svg":false,"png":true},"icon":{"svg":false,"png":true}},"rabitabank_ojsc":{"logo":{"svg":false,"png":true},"icon":{"svg":false,"png":true}},"famsa":{"logo":{"svg":false,"png":true}},"link":{"logo":{"svg":true,"png":false},"icon":{"svg":true,"png":false}},"macro":{"logo":{"svg":false,"png":true},"icon":{"svg":false,"png":true}},"elo":{"logo":{"svg":false,"png":true},"icon":{"svg":false,"png":true}},"interkassa":{"logo":{"svg":true,"png":false},"icon":{"svg":true,"png":false}},"china_minsheng_bank":{"logo":{"svg":false,"png":true},"icon":{"svg":true,"png":false}},"ibox":{"logo":{"svg":true,"png":false},"icon":{"svg":true,"png":false}},"settlepay_wallet":{"logo":{"svg":true,"png":false},"icon":{"svg":true,"png":false}},"icicinetbanking":{"logo":{"svg":false,"png":true},"icon":{"svg":false,"png":true}},"banco_pichincha_cash":{"logo":{"svg":false,"png":true},"icon":{"svg":false,"png":true}},"oxxo":{"logo":{"svg":true,"png":false},"icon":{"svg":true,"png":false}},"tas24":{"icon":{"svg":false,"png":true}},"tenpay":{"logo":{"svg":false,"png":true},"icon":{"svg":false,"png":true}},"7eleven":{"logo":{"svg":false,"png":true},"icon":{"svg":false,"png":true}},"caja_arequipa_cash":{"logo":{"svg":false,"png":true},"icon":{"svg":false,"png":true}},"nordeasolo":{"logo":{"svg":true,"png":false},"icon":{"svg":true,"png":false}},"binance_usd":{"logo":{"svg":false,"png":true},"icon":{"svg":false,"png":true}},"pingping":{"logo":{"svg":false,"png":true},"icon":{"svg":false,"png":true}},"banco_de_chile":{"logo":{"svg":false,"png":true},"icon":{"svg":false,"png":true}},"supervielle":{"logo":{"svg":false,"png":true},"icon":{"svg":false,"png":true}},"vietin_bank":{"logo":{"svg":false,"png":true},"icon":{"svg":false,"png":true}},"citibank_korea":{"logo":{"svg":true,"png":false},"icon":{"svg":true,"png":false}},"bac_a_bank":{"logo":{"svg":false,"png":true},"icon":{"svg":false,"png":true}},"dutch_bangla_bank_limited_rocket":{"logo":{"svg":false,"png":true},"icon":{"svg":false,"png":true}},"united_bank_of_india":{"logo":{"svg":true,"png":false},"icon":{"svg":true,"png":false}},"creditagricole":{"logo":{"svg":false,"png":true},"icon":{"svg":false,"png":true}},"fakturaru":{"logo":{"svg":false,"png":true},"icon":{"svg":false,"png":true}},"permata_bank":{"logo":{"svg":true,"png":false},"icon":{"svg":true,"png":false}},"tether":{"logo":{"svg":true,"png":false},"icon":{"svg":true,"png":false}},"viet_bank":{"logo":{"svg":false,"png":true},"icon":{"svg":false,"png":true}},"kapital_bank_ojsc":{"logo":{"svg":false,"png":true},"icon":{"svg":false,"png":true}},"vodafone_mpesa":{"logo":{"svg":false,"png":true},"icon":{"svg":false,"png":true}},"cimbclicksinternetbanking":{"logo":{"svg":false,"png":true},"icon":{"svg":false,"png":true}},"cimb_bank":{"logo":{"svg":true,"png":true},"icon":{"svg":true,"png":true}},"standard_charter_bank":{"logo":{"svg":true,"png":false},"icon":{"svg":true,"png":false}},"jyskebank":{"logo":{"svg":false,"png":true},"icon":{"svg":false,"png":true}},"paydirekt":{"logo":{"svg":true,"png":false},"icon":{"svg":true,"png":false}},"vietcom_bank":{"logo":{"svg":true,"png":false},"icon":{"svg":true,"png":false}},"paysbuy":{"logo":{"svg":false,"png":true},"icon":{"svg":false,"png":true}},"usd_coin":{"icon":{"svg":false,"png":true},"logo":{"svg":true,"png":false}},"pagofacil":{"logo":{"svg":false,"png":true},"icon":{"svg":false,"png":true}},"public_bank_fpx":{"logo":{"svg":true,"png":false},"icon":{"svg":true,"png":false}},"afirme_online_banking":{"logo":{"svg":true,"png":false},"icon":{"svg":true,"png":false}},"corporation_bank":{"logo":{"svg":true,"png":false},"icon":{"svg":true,"png":false}},"alfaclick":{"logo":{"svg":false,"png":true},"icon":{"svg":false,"png":true}},"scbbanknetbanking":{"logo":{"svg":false,"png":true},"icon":{"svg":false,"png":true}},"perfectmoney":{"logo":{"svg":false,"png":true},"icon":{"svg":true,"png":false}},"busan_bank":{"logo":{"svg":false,"png":true},"icon":{"svg":false,"png":true}},"skrill":{"logo":{"svg":true,"png":false},"icon":{"svg":true,"png":false}},"saastopankki":{"logo":{"svg":false,"png":true},"icon":{"svg":false,"png":true}},"megafon":{"logo":{"svg":false,"png":true},"icon":{"svg":false,"png":true}},"aktia":{"logo":{"svg":false,"png":true},"icon":{"svg":false,"png":true}},"lakshmi_vilas_bank_india":{"logo":{"svg":false,"png":true},"icon":{"svg":false,"png":true}},"svyaznoy":{"logo":{"svg":false,"png":true},"icon":{"svg":false,"png":true}},"banco_azteca_cash":{"logo":{"svg":false,"png":true},"icon":{"svg":false,"png":true}},"rupaypaysecure":{"logo":{"svg":false,"png":true},"icon":{"svg":false,"png":true}},"bank_of_china":{"logo":{"svg":true,"png":false},"icon":{"svg":true,"png":false}},"ticketpremium":{"logo":{"svg":false,"png":true},"icon":{"svg":false,"png":true}},"bank_of_baroda":{"logo":{"svg":true,"png":false},"icon":{"svg":true,"png":false}},"tarjetanaranjacreditcard":{"logo":{"svg":false,"png":true},"icon":{"svg":false,"png":true}},"public_bank":{"logo":{"svg":true,"png":false},"icon":{"svg":true,"png":false}},"directdebit":{"logo":{"svg":false,"png":true},"icon":{"svg":false,"png":true}},"rapipago":{"logo":{"svg":false,"png":true},"icon":{"svg":false,"png":true}},"indovina_bank":{"logo":{"svg":false,"png":true},"icon":{"svg":false,"png":true}},"gp_bank":{"logo":{"svg":false,"png":true},"icon":{"svg":false,"png":true}},"krungsrinetbanking":{"logo":{"svg":false,"png":true},"icon":{"svg":false,"png":true}},"bbva_continental":{"logo":{"svg":false,"png":true},"icon":{"svg":false,"png":true}},"bancopastor":{"logo":{"svg":false,"png":true},"icon":{"svg":false,"png":true}},"pay4fun":{"logo":{"svg":false,"png":true},"icon":{"svg":false,"png":true}},"ecocash":{"logo":{"svg":false,"png":true},"icon":{"svg":false,"png":true}},"mastercarddebit":{"logo":{"svg":false,"png":true},"icon":{"svg":false,"png":true}},"cimb_bank_fpx":{"logo":{"svg":true,"png":false},"icon":{"svg":true,"png":false}},"multibanco":{"logo":{"svg":false,"png":true},"icon":{"svg":false,"png":true}},"instantcredit":{"logo":{"svg":false,"png":true},"icon":{"svg":false,"png":true}},"korea_development_bank":{"logo":{"svg":false,"png":true},"icon":{"svg":false,"png":true}},"ssk_ge":{"logo":{"svg":false,"png":true},"icon":{"svg":false,"png":true}},"freecharge":{"logo":{"svg":true,"png":false},"icon":{"svg":true,"png":false}},"inteligo":{"logo":{"svg":false,"png":true},"icon":{"svg":false,"png":true}},"banco_falabella":{"logo":{"svg":false,"png":true},"icon":{"svg":false,"png":true}},"imps":{"logo":{"svg":false,"png":true},"icon":{"svg":false,"png":true}},"barzahlen":{"logo":{"svg":false,"png":true},"icon":{"svg":false,"png":true}},"promsvyazbank":{"logo":{"svg":false,"png":true},"icon":{"svg":false,"png":true}},"shopeepay":{"logo":{"svg":true,"png":false},"icon":{"svg":true,"png":false}},"toncoin":{"logo":{"svg":false,"png":true},"icon":{"svg":false,"png":true}},"vib_bank":{"icon":{"svg":false,"png":true}},"reliance_jio":{"logo":{"svg":true,"png":false},"icon":{"svg":true,"png":false}},"roma":{"logo":{"svg":true,"png":false},"icon":{"svg":true,"png":false}},"investec_bank":{"logo":{"svg":false,"png":true},"icon":{"svg":false,"png":true}},"mefete":{"logo":{"svg":false,"png":true},"icon":{"svg":false,"png":true}},"teleingreso":{"logo":{"svg":false,"png":true},"icon":{"svg":false,"png":true}},"santander":{"logo":{"svg":false,"png":true},"icon":{"svg":false,"png":true}},"la_banque_postale":{"logo":{"svg":true,"png":false},"icon":{"svg":true,"png":false}},"tescolotus":{"logo":{"svg":false,"png":true},"icon":{"svg":false,"png":true}},"upi":{"logo":{"svg":true,"png":false},"icon":{"svg":true,"png":false}},"redcompra":{"logo":{"svg":true,"png":false},"icon":{"svg":true,"png":false}},"m10":{"logo":{"svg":false,"png":true},"icon":{"svg":false,"png":true}},"ovo":{"logo":{"svg":false,"png":true},"icon":{"svg":false,"png":true}},"rixty":{"logo":{"svg":false,"png":true},"icon":{"svg":false,"png":true}},"zapp":{"logo":{"svg":false,"png":true},"icon":{"svg":false,"png":true}},"instant_papara":{"logo":{"svg":true,"png":false},"icon":{"svg":true,"png":false}},"qazkombank":{"logo":{"svg":false,"png":true},"icon":{"svg":false,"png":true}},"wiretransfer":{"logo":{"svg":true,"png":false},"icon":{"svg":true,"png":false}},"shinhan_bank":{"logo":{"svg":true,"png":false},"icon":{"svg":true,"png":false}},"qiwi":{"logo":{"svg":true,"png":false},"icon":{"svg":true,"png":false}},"boleto_bancario":{"logo":{"svg":false,"png":true},"icon":{"svg":false,"png":true}},"parazula":{"logo":{"svg":false,"png":true},"icon":{"svg":false,"png":true}},"swiffy_eft":{"logo":{"svg":false,"png":true},"icon":{"svg":false,"png":true}},"esewa":{"logo":{"svg":false,"png":true},"icon":{"svg":false,"png":true}},"banamex":{"logo":{"svg":true,"png":false},"icon":{"svg":true,"png":false}},"mandiri_bank":{"logo":{"svg":true,"png":false},"icon":{"svg":true,"png":false}},"gatepay":{"logo":{"svg":false,"png":true},"icon":{"svg":false,"png":true}},"express_lider_cash":{"logo":{"svg":false,"png":true},"icon":{"svg":false,"png":true}},"onecard":{"logo":{"svg":false,"png":true},"icon":{"svg":false,"png":true}},"twopayler":{"icon":{"svg":false,"png":true},"logo":{"svg":true,"png":false}},"banco_de_antigua_cash":{"logo":{"svg":false,"png":true},"icon":{"svg":false,"png":true}},"sibs_mbway":{"icon":{"svg":false,"png":true},"logo":{"svg":true,"png":false}},"ssk_kz":{"logo":{"svg":false,"png":true},"icon":{"svg":false,"png":true}},"bizum":{"logo":{"svg":false,"png":true},"icon":{"svg":false,"png":true}},"nsmep":{"logo":{"svg":false,"png":true},"icon":{"svg":false,"png":true}},"touchngo":{"logo":{"svg":true,"png":false},"icon":{"svg":true,"png":false}},"rcbc":{"logo":{"svg":true,"png":false},"icon":{"svg":true,"png":false}},"bangkokbanknetbanking":{"logo":{"svg":false,"png":true},"icon":{"svg":false,"png":true}},"forexbank":{"logo":{"svg":false,"png":true},"icon":{"svg":false,"png":true}},"advcash":{"logo":{"svg":true,"png":false},"icon":{"svg":true,"png":false}},"vtb24":{"logo":{"svg":false,"png":true},"icon":{"svg":false,"png":true}},"mts":{"logo":{"svg":false,"png":true},"icon":{"svg":false,"png":true}},"mbank":{"logo":{"svg":false,"png":true},"icon":{"svg":false,"png":true}},"payment_card":{"logo":{"svg":true,"png":false},"icon":{"svg":true,"png":false}},"zen_wallet":{"logo":{"svg":true,"png":false},"icon":{"svg":true,"png":false}},"a_cuenta_cash":{"logo":{"svg":false,"png":true},"icon":{"svg":false,"png":true}},"phonepe":{"logo":{"svg":true,"png":false},"icon":{"svg":true,"png":false}},"imepay":{"logo":{"svg":true,"png":false},"icon":{"svg":true,"png":false}},"perfectmoney_voucher":{"logo":{"svg":false,"png":true},"icon":{"svg":true,"png":false}},"woori_bank":{"logo":{"svg":false,"png":true},"icon":{"svg":false,"png":true}},"hdfcbanknetbankingindia":{"logo":{"svg":false,"png":true},"icon":{"svg":false,"png":true}},"paymentrush":{"logo":{"svg":false,"png":true},"icon":{"svg":false,"png":true}},"standardbank":{"logo":{"svg":false,"png":true},"icon":{"svg":false,"png":true}},"maritime_bank":{"logo":{"svg":false,"png":true},"icon":{"svg":false,"png":true}},"axis_bank":{"logo":{"svg":true,"png":false},"icon":{"svg":true,"png":false}},"mobikwik":{"logo":{"svg":false,"png":true},"icon":{"svg":false,"png":true}},"vvvgiftcard":{"logo":{"svg":false,"png":true},"icon":{"svg":false,"png":true}},"kriita2":{"logo":{"svg":false,"png":true},"icon":{"svg":false,"png":true}},"pumb":{"logo":{"svg":false,"png":true},"icon":{"svg":false,"png":true}},"caja_trujillo_cash":{"logo":{"svg":false,"png":true},"icon":{"svg":false,"png":true}},"jcb":{"logo":{"svg":false,"png":true},"icon":{"svg":false,"png":true}},"flexepinemoneyvouchers":{"logo":{"svg":false,"png":true},"icon":{"svg":false,"png":true}},"perfectmoney_account":{"logo":{"svg":false,"png":true},"icon":{"svg":true,"png":false}},"afterpay":{"logo":{"svg":false,"png":true},"icon":{"svg":false,"png":true}},"qnb_finansbank":{"logo":{"svg":true,"png":false},"icon":{"svg":true,"png":false}},"erstebank":{"logo":{"svg":false,"png":true},"icon":{"svg":false,"png":true}},"dankort":{"logo":{"svg":false,"png":true},"icon":{"svg":false,"png":true}},"centpays":{"logo":{"svg":false,"png":true},"icon":{"svg":false,"png":true}},"jeton_wallet":{"logo":{"svg":false,"png":true},"icon":{"svg":false,"png":true}},"icabanken":{"logo":{"svg":false,"png":true},"icon":{"svg":false,"png":true}},"bank_negara_indonesia_va":{"logo":{"svg":true,"png":false},"icon":{"svg":true,"png":false}},"kasikorn_bank":{"logo":{"svg":true,"png":false},"icon":{"svg":true,"png":false}},"moneta":{"logo":{"svg":false,"png":true},"icon":{"svg":false,"png":true}},"walmart_express":{"logo":{"svg":true,"png":false},"icon":{"svg":true,"png":false}},"stripe":{"logo":{"svg":true,"png":false},"icon":{"svg":true,"png":false}},"frenchonlinepaymentmethodewalletpaylib":{"logo":{"svg":false,"png":true},"icon":{"svg":false,"png":true}},"otpbank":{"logo":{"svg":false,"png":true},"icon":{"svg":false,"png":true}},"usemyservices":{"logo":{"svg":false,"png":true},"icon":{"svg":false,"png":true}},"rbkmoney":{"logo":{"svg":false,"png":true},"icon":{"svg":false,"png":true}},"enetsdirectdebit":{"logo":{"svg":false,"png":true},"icon":{"svg":false,"png":true}},"citadelelatvia":{"logo":{"svg":false,"png":true},"icon":{"svg":false,"png":true}},"calypso_pay_ltd_gateexpress":{"icon":{"svg":false,"png":true},"logo":{"svg":true,"png":false}},"monobank":{"logo":{"svg":false,"png":true},"icon":{"svg":false,"png":true}},"ing":{"logo":{"svg":false,"png":true},"icon":{"svg":false,"png":true}},"china_construction_bank":{"logo":{"svg":true,"png":false},"icon":{"svg":true,"png":false}},"erip":{"logo":{"svg":false,"png":true},"icon":{"svg":false,"png":true}},"mobilum":{"logo":{"svg":false,"png":true},"icon":{"svg":false,"png":true}},"redcompraalternativeonlinepaymentmethodchile":{"logo":{"svg":false,"png":true},"icon":{"svg":false,"png":true}},"palmpay":{"logo":{"svg":false,"png":true},"icon":{"svg":false,"png":true}},"absa_bank":{"logo":{"svg":false,"png":true},"icon":{"svg":false,"png":true}},"red_activa_cash":{"logo":{"svg":false,"png":true},"icon":{"svg":false,"png":true}},"calypso_pay_ltd_empayre":{"icon":{"svg":false,"png":true},"logo":{"svg":true,"png":false}},"capitec_bank":{"logo":{"svg":false,"png":true},"icon":{"svg":false,"png":true}},"trustly_paynplay":{"icon":{"svg":false,"png":true},"logo":{"svg":true,"png":false}},"sofortbanking":{"logo":{"svg":true,"png":false},"icon":{"svg":true,"png":false}},"tranzzo":{"logo":{"svg":false,"png":true},"icon":{"svg":false,"png":true}},"banco_guayaquil_cash":{"logo":{"svg":false,"png":true},"icon":{"svg":false,"png":true}},"achdebits":{"logo":{"svg":false,"png":true},"icon":{"svg":false,"png":true}},"ideal_crypto":{"logo":{"svg":true,"png":false},"icon":{"svg":true,"png":false}},"neteller":{"icon":{"svg":false,"png":true},"logo":{"svg":true,"png":false}},"russian_standart_bank":{"logo":{"svg":false,"png":true},"icon":{"svg":false,"png":true}},"mazooma":{"logo":{"svg":false,"png":true},"icon":{"svg":false,"png":true}},"komercnibanka":{"logo":{"svg":false,"png":true},"icon":{"svg":false,"png":true}},"kvitum":{"logo":{"svg":true,"png":false},"icon":{"svg":true,"png":false}},"punjab_national_bank":{"logo":{"svg":true,"png":false},"icon":{"svg":true,"png":false}},"ceskasporitelna":{"logo":{"svg":false,"png":true},"icon":{"svg":false,"png":true}},"daegu_bank":{"logo":{"svg":false,"png":true},"icon":{"svg":false,"png":true}},"china_everbright_bank":{"logo":{"svg":true,"png":false},"icon":{"svg":true,"png":false}},"nixmoney":{"logo":{"svg":false,"png":true},"icon":{"svg":false,"png":true}},"applepay":{"logo":{"svg":true,"png":false},"icon":{"svg":true,"png":false}},"cfc_bank":{"logo":{"svg":false,"png":true},"icon":{"svg":false,"png":true}},"exmo":{"logo":{"svg":false,"png":true},"icon":{"svg":false,"png":true}},"wilobank":{"logo":{"svg":false,"png":true},"icon":{"svg":false,"png":true}},"agricultural_bank_of_china":{"logo":{"svg":true,"png":false},"icon":{"svg":true,"png":false}},"neosurf":{"logo":{"svg":false,"png":true},"icon":{"svg":false,"png":true}},"grabpay":{"logo":{"svg":false,"png":true},"icon":{"svg":false,"png":true}},"minitix":{"logo":{"svg":false,"png":true},"icon":{"svg":false,"png":true}},"vodafone_pay":{"icon":{"svg":false,"png":true},"logo":{"svg":true,"png":false}},"standard_chartered_bank_malaysia_fpx":{"logo":{"svg":true,"png":false},"icon":{"svg":true,"png":false}},"payzapp":{"logo":{"svg":false,"png":true},"icon":{"svg":false,"png":true}},"dana":{"logo":{"svg":false,"png":true},"icon":{"svg":false,"png":true}},"caja_tacna":{"logo":{"svg":false,"png":true},"icon":{"svg":false,"png":true}},"uco_bank_india":{"logo":{"svg":false,"png":true},"icon":{"svg":false,"png":true}},"nam_a_bank":{"logo":{"svg":false,"png":true},"icon":{"svg":false,"png":true}},"qqpay":{"logo":{"svg":true,"png":false},"icon":{"svg":true,"png":false}},"bank_transfer":{"logo":{"svg":true,"png":false},"icon":{"svg":true,"png":false}},"ecopayz":{"logo":{"svg":true,"png":false},"icon":{"svg":true,"png":false}},"mypaywizard":{"logo":{"svg":false,"png":true},"icon":{"svg":false,"png":true}},"interac_crypto":{"logo":{"svg":false,"png":true},"icon":{"svg":false,"png":true}},"cash":{"logo":{"svg":true,"png":true},"icon":{"svg":true,"png":true}},"bank_neo_commerce":{"logo":{"svg":false,"png":true},"icon":{"svg":false,"png":true}},"cartebancaires":{"logo":{"svg":false,"png":true},"icon":{"svg":false,"png":true}},"bankinter":{"logo":{"svg":false,"png":true},"icon":{"svg":false,"png":true}},"ecobanq":{"logo":{"svg":false,"png":true},"icon":{"svg":false,"png":true}},"ping_an_bank":{"logo":{"svg":true,"png":false},"icon":{"svg":true,"png":false}},"shamrao_vithal_cooperative_bank_india":{"logo":{"svg":false,"png":true},"icon":{"svg":false,"png":true}},"uob_fpx":{"logo":{"svg":true,"png":false},"icon":{"svg":true,"png":false}},"khipu":{"logo":{"svg":false,"png":true},"icon":{"svg":false,"png":true}},"oppohjola":{"logo":{"svg":false,"png":true},"icon":{"svg":false,"png":true}},"raiffeisenbank":{"logo":{"svg":true,"png":false},"icon":{"svg":true,"png":false}},"zalopay":{"logo":{"svg":true,"png":false},"icon":{"svg":true,"png":false}},"baoviet_bank":{"logo":{"svg":false,"png":true},"icon":{"svg":false,"png":true}},"turkiye_finans_katilim_bankasi_as":{"logo":{"svg":false,"png":true},"icon":{"svg":false,"png":true}},"cosmos_bank_india":{"logo":{"svg":false,"png":true},"icon":{"svg":false,"png":true}},"wmcard":{"logo":{"svg":false,"png":true},"icon":{"svg":false,"png":true}},"stellar":{"logo":{"svg":false,"png":true},"icon":{"svg":false,"png":true}},"bank_card":{"logo":{"svg":true,"png":false},"icon":{"svg":true,"png":false}},"binancepay":{"logo":{"svg":true,"png":false},"icon":{"svg":true,"png":false}},"pagoefectivo":{"logo":{"svg":false,"png":true},"icon":{"svg":false,"png":true}},"alphapo":{"logo":{"svg":false,"png":true},"icon":{"svg":false,"png":true}},"kwixo":{"logo":{"svg":false,"png":true},"icon":{"svg":false,"png":true}},"industrial_bank_hanoi":{"logo":{"svg":false,"png":true},"icon":{"svg":false,"png":true}},"sebbank":{"logo":{"svg":false,"png":true},"icon":{"svg":false,"png":true}},"gopay":{"icon":{"svg":false,"png":true},"logo":{"svg":true,"png":false}},"giropay":{"logo":{"svg":true,"png":false},"icon":{"svg":true,"png":false}},"girocard":{"logo":{"svg":false,"png":true},"icon":{"svg":false,"png":true}},"federal_bank_india":{"logo":{"svg":false,"png":true},"icon":{"svg":false,"png":true}},"mi_comisariato_cash":{"logo":{"svg":false,"png":true},"icon":{"svg":false,"png":true}},"octopus":{"logo":{"svg":false,"png":true},"icon":{"svg":false,"png":true}},"Self service kiosk Belarus":{"logo":{"svg":false,"png":true},"icon":{"svg":false,"png":true}},"industrial_and_commercial_bank_of_china":{"logo":{"svg":true,"png":false},"icon":{"svg":true,"png":false}},"bancodobrasil":{"logo":{"svg":true,"png":false},"icon":{"svg":true,"png":false}},"banamexdebitcardonlinepaymentmethodmexico":{"logo":{"svg":false,"png":true},"icon":{"svg":false,"png":true}},"polkadot":{"logo":{"svg":false,"png":true},"icon":{"svg":false,"png":true}},"va_may_bank":{"logo":{"svg":true,"png":false},"icon":{"svg":true,"png":false}},"garanti_bbva":{"logo":{"svg":false,"png":true},"icon":{"svg":false,"png":true}},"bunq":{"logo":{"svg":false,"png":true},"icon":{"svg":false,"png":true}},"airteltigo":{"logo":{"svg":false,"png":true},"icon":{"svg":false,"png":true}},"ripple":{"logo":{"svg":true,"png":false},"icon":{"svg":true,"png":false}},"vodafone_cash":{"icon":{"svg":false,"png":true},"logo":{"svg":true,"png":false}},"nonghyup_bank":{"logo":{"svg":false,"png":true},"icon":{"svg":false,"png":true}},"ciberpay":{"logo":{"svg":false,"png":true},"icon":{"svg":false,"png":true}},"bancontact":{"logo":{"svg":false,"png":true},"icon":{"svg":false,"png":true}},"state_bank_of_india":{"logo":{"svg":true,"png":false},"icon":{"svg":true,"png":false}},"test":{"logo":{"svg":false,"png":true},"icon":{"svg":true,"png":false}},"orange_cash":{"logo":{"svg":false,"png":true},"icon":{"svg":false,"png":true}},"banorte_online_banking":{"logo":{"svg":true,"png":false},"icon":{"svg":true,"png":false}},"tatrabanka":{"logo":{"svg":false,"png":true},"icon":{"svg":false,"png":true}},"banco_de_credito_cash":{"logo":{"svg":false,"png":true},"icon":{"svg":false,"png":true}},"sepacredittransfer":{"logo":{"svg":true,"png":false},"icon":{"svg":true,"png":false}},"ivrbilling":{"logo":{"svg":false,"png":true},"icon":{"svg":false,"png":true}},"cimb_clicks_indonesia":{"logo":{"svg":false,"png":true},"icon":{"svg":false,"png":true}},"extra":{"logo":{"svg":true,"png":false},"icon":{"svg":true,"png":false}},"ncb_bank":{"logo":{"svg":false,"png":true},"icon":{"svg":false,"png":true}},"maestro":{"logo":{"svg":true,"png":false},"icon":{"svg":true,"png":false}},"masterpass":{"logo":{"svg":false,"png":true},"icon":{"svg":false,"png":true}},"bidv_bank":{"logo":{"svg":true,"png":false},"icon":{"svg":true,"png":false}},"efecty":{"logo":{"svg":true,"png":false},"icon":{"svg":true,"png":false}},"advcash_wallet":{"logo":{"svg":true,"png":false},"icon":{"svg":true,"png":false}},"efectyonlinecashpaymentmethodscolombia":{"logo":{"svg":false,"png":true},"icon":{"svg":false,"png":true}},"vpay":{"logo":{"svg":false,"png":true},"icon":{"svg":false,"png":true}},"societe_generale_bank":{"logo":{"svg":false,"png":true},"icon":{"svg":false,"png":true}},"china_merchants_bank":{"logo":{"svg":true,"png":false},"icon":{"svg":true,"png":false}},"banco_nacional":{"logo":{"svg":false,"png":true},"icon":{"svg":false,"png":true}},"cryptomus":{"logo":{"svg":true,"png":false},"icon":{"svg":true,"png":false}},"maybanknetbankingphillipines":{"logo":{"svg":false,"png":true},"icon":{"svg":false,"png":true}},"blik":{"logo":{"svg":false,"png":true},"icon":{"svg":false,"png":true}},"unitedoverseasbankuobnetbanking":{"logo":{"svg":false,"png":true},"icon":{"svg":false,"png":true}},"csb_bank":{"logo":{"svg":false,"png":true},"icon":{"svg":false,"png":true}},"pichincha_mi_vecino_cash":{"logo":{"svg":false,"png":true},"icon":{"svg":false,"png":true}},"rhb_bank":{"logo":{"svg":true,"png":false},"icon":{"svg":true,"png":false}},"australia_and_new_zealand_banking_group":{"logo":{"svg":true,"png":false},"icon":{"svg":true,"png":false}},"payskin":{"logo":{"svg":true,"png":false},"icon":{"svg":true,"png":false}},"bbva_bancomer":{"logo":{"svg":true,"png":false},"icon":{"svg":true,"png":false}},"postbank":{"logo":{"svg":false,"png":true},"icon":{"svg":false,"png":true}},"postepay":{"logo":{"svg":false,"png":true},"icon":{"svg":false,"png":true}},"spush_pay":{"logo":{"svg":true,"png":false},"icon":{"svg":true,"png":false}},"first_national_bank":{"logo":{"svg":false,"png":true},"icon":{"svg":false,"png":true}},"bancontactmistercash":{"logo":{"svg":false,"png":true},"icon":{"svg":false,"png":true}},"viabalotoonlinecashpaymentmethodscolombia":{"logo":{"svg":false,"png":true},"icon":{"svg":false,"png":true}},"okpay_finance_ltd_slyse":{"logo":{"svg":false,"png":true},"icon":{"svg":false,"png":true}},"safaricom":{"logo":{"svg":false,"png":true},"icon":{"svg":false,"png":true}},"dai_coin":{"logo":{"svg":false,"png":true},"icon":{"svg":false,"png":true}},"j_k_bank_india":{"logo":{"svg":false,"png":true},"icon":{"svg":false,"png":true}},"247billpay":{"logo":{"svg":false,"png":true},"icon":{"svg":false,"png":true}},"interbank":{"logo":{"svg":false,"png":true},"icon":{"svg":false,"png":true}},"caja_huancayo":{"logo":{"svg":false,"png":true},"icon":{"svg":false,"png":true}},"uobt":{"logo":{"svg":true,"png":false},"icon":{"svg":true,"png":false}},"eps":{"logo":{"svg":false,"png":true},"icon":{"svg":false,"png":true}},"commerzbank":{"logo":{"svg":true,"png":false},"icon":{"svg":true,"png":false}},"magnacreditcardsonlinepaymentmethodschile":{"logo":{"svg":false,"png":true},"icon":{"svg":false,"png":true}},"kviku":{"logo":{"svg":false,"png":true},"icon":{"svg":false,"png":true}},"Self service kiosk Moldova":{"logo":{"svg":false,"png":true},"icon":{"svg":false,"png":true}},"unistream":{"logo":{"svg":false,"png":true},"icon":{"svg":false,"png":true}},"bancobrasil":{"logo":{"svg":false,"png":true},"icon":{"svg":false,"png":true}},"raggett_limited_paycos":{"icon":{"svg":false,"png":true},"logo":{"svg":true,"png":false}},"moneytopay":{"logo":{"svg":false,"png":true},"icon":{"svg":false,"png":true}},"wechat":{"logo":{"svg":true,"png":false},"icon":{"svg":true,"png":false}},"capayable":{"logo":{"svg":false,"png":true},"icon":{"svg":false,"png":true}},"ssk_ua":{"logo":{"svg":false,"png":true},"icon":{"svg":false,"png":true}},"primabanka":{"logo":{"svg":false,"png":true},"icon":{"svg":false,"png":true}},"zantel_ezypesa":{"logo":{"svg":false,"png":true},"icon":{"svg":false,"png":true}},"provinciapagos":{"logo":{"svg":false,"png":true},"icon":{"svg":false,"png":true}},"sencillitoalternativecashpaymentmethodschile":{"logo":{"svg":false,"png":true},"icon":{"svg":false,"png":true}},"sacom_bank":{"logo":{"svg":false,"png":true},"icon":{"svg":false,"png":true}},"cifrograd":{"logo":{"svg":false,"png":true},"icon":{"svg":false,"png":true}},"billink":{"logo":{"svg":false,"png":true},"icon":{"svg":false,"png":true}},"paynet":{"logo":{"svg":true,"png":false},"icon":{"svg":true,"png":false}},"platform_m10_mmc_pashapay":{"logo":{"svg":false,"png":true},"icon":{"svg":false,"png":true}},"fawry_crypto":{"logo":{"svg":false,"png":true},"icon":{"svg":false,"png":true}},"swedbank":{"logo":{"svg":false,"png":true},"icon":{"svg":false,"png":true}},"karurvysya_bank_india":{"logo":{"svg":true,"png":false},"icon":{"svg":true,"png":false}},"okpay":{"logo":{"svg":false,"png":true},"icon":{"svg":false,"png":true}},"olamoney":{"logo":{"svg":false,"png":true},"icon":{"svg":false,"png":true}},"papercheck":{"logo":{"svg":false,"png":true},"icon":{"svg":false,"png":true}},"baz_superapp":{"logo":{"svg":true,"png":false},"icon":{"svg":true,"png":false}},"bankia":{"logo":{"svg":false,"png":true},"icon":{"svg":false,"png":true}},"circulo_k":{"logo":{"svg":true,"png":false},"icon":{"svg":true,"png":false}},"venom":{"icon":{"svg":false,"png":true},"logo":{"svg":true,"png":false}},"yota":{"logo":{"svg":false,"png":true},"icon":{"svg":false,"png":true}},"bancodobrasilcomercioeletronico":{"logo":{"svg":false,"png":true},"icon":{"svg":false,"png":true}},"chinaunionpay":{"logo":{"svg":true,"png":false},"icon":{"svg":true,"png":false}},"coingate":{"logo":{"svg":true,"png":false},"icon":{"svg":true,"png":false}},"astropay_wallet":{"logo":{"svg":false,"png":true},"icon":{"svg":false,"png":true}},"bybit_pay":{"logo":{"svg":false,"png":true},"icon":{"svg":false,"png":true}},"muchbetter":{"logo":{"svg":true,"png":false},"icon":{"svg":true,"png":false}},"payzippy":{"logo":{"svg":false,"png":true},"icon":{"svg":false,"png":true}},"postfinanceefinance":{"logo":{"svg":false,"png":true},"icon":{"svg":false,"png":true}},"unicredit":{"logo":{"svg":false,"png":true},"icon":{"svg":false,"png":true}},"banco_estado":{"logo":{"svg":false,"png":true},"icon":{"svg":false,"png":true}},"seven_eleven":{"logo":{"svg":true,"png":false},"icon":{"svg":true,"png":false}},"akbank":{"icon":{"svg":false,"png":true},"logo":{"svg":true,"png":false}},"googlewallet":{"logo":{"svg":true,"png":false},"icon":{"svg":true,"png":false}},"city_union_bank":{"logo":{"svg":true,"png":false},"icon":{"svg":true,"png":false}},"kbcbetaalknop":{"logo":{"svg":false,"png":true},"icon":{"svg":false,"png":true}},"kasnet_cash":{"logo":{"svg":false,"png":true},"icon":{"svg":false,"png":true}},"postpay":{"logo":{"svg":false,"png":true},"icon":{"svg":false,"png":true}},"cimb_clicks_bank":{"logo":{"svg":false,"png":true},"icon":{"svg":false,"png":true}},"uatp":{"logo":{"svg":false,"png":true},"icon":{"svg":false,"png":true}},"bancnetdirectdebits":{"logo":{"svg":false,"png":true},"icon":{"svg":false,"png":true}},"halotel":{"logo":{"svg":false,"png":true},"icon":{"svg":false,"png":true}},"debitobradesco":{"logo":{"svg":false,"png":true},"icon":{"svg":false,"png":true}},"alipay":{"logo":{"svg":true,"png":false},"icon":{"svg":true,"png":false}},"hsbc":{"logo":{"svg":false,"png":true},"icon":{"svg":false,"png":true}},"scotiabank":{"logo":{"svg":false,"png":true},"icon":{"svg":false,"png":true}},"cashu":{"logo":{"svg":false,"png":true},"icon":{"svg":false,"png":true}},"exim_bank":{"logo":{"svg":true,"png":false},"icon":{"svg":true,"png":false}},"rabobank":{"logo":{"svg":false,"png":true},"icon":{"svg":false,"png":true}},"paypal":{"logo":{"svg":true,"png":false},"icon":{"svg":true,"png":false}},"webpayplus":{"logo":{"svg":true,"png":false},"icon":{"svg":true,"png":false}},"dcb_bank_india":{"logo":{"svg":false,"png":true},"icon":{"svg":false,"png":true}},"suhyup_bank":{"logo":{"svg":false,"png":true},"icon":{"svg":false,"png":true}},"united_commercial_bank_upay":{"logo":{"svg":false,"png":true},"icon":{"svg":false,"png":true}},"hong_leong_bank_fpx":{"logo":{"svg":true,"png":false},"icon":{"svg":true,"png":false}},"snapscan_qr":{"logo":{"svg":false,"png":true},"icon":{"svg":true,"png":false}},"sbp_tome_qr":{"logo":{"svg":true,"png":false},"icon":{"svg":true,"png":false}},"Self service kiosk Russia":{"logo":{"svg":false,"png":true},"icon":{"svg":false,"png":true}},"coins_ph":{"logo":{"svg":false,"png":true},"icon":{"svg":false,"png":true}},"tron":{"icon":{"svg":false,"png":true},"logo":{"svg":true,"png":false}},"maya":{"logo":{"svg":true,"png":false},"icon":{"svg":true,"png":false}},"aktivbank":{"logo":{"svg":false,"png":true},"icon":{"svg":false,"png":true}},"geopaynet":{"logo":{"svg":true,"png":false},"icon":{"svg":true,"png":false}},"litecoin":{"logo":{"svg":false,"png":true},"icon":{"svg":false,"png":true}},"privat24":{"logo":{"svg":true,"png":false},"icon":{"svg":true,"png":false}},"bradescocomercioeletronico":{"logo":{"svg":false,"png":true},"icon":{"svg":false,"png":true}},"deutsche_bank":{"logo":{"svg":false,"png":true},"icon":{"svg":false,"png":true}},"farmacia_la_mas_barata":{"logo":{"svg":true,"png":false},"icon":{"svg":true,"png":false}},"banco_santander":{"logo":{"svg":false,"png":true},"icon":{"svg":false,"png":true}},"equitel":{"logo":{"svg":false,"png":true},"icon":{"svg":false,"png":true}},"ingpl":{"logo":{"svg":true,"png":false},"icon":{"svg":true,"png":false}},"scotiabank_cash":{"logo":{"svg":false,"png":true},"icon":{"svg":false,"png":true}},"cashlib_voucher":{"logo":{"svg":false,"png":true},"icon":{"svg":false,"png":true}},"standard_chartered_bank_vietnam":{"logo":{"svg":false,"png":true},"icon":{"svg":false,"png":true}},"azer_turk_bank_ojsc":{"logo":{"svg":false,"png":true},"icon":{"svg":false,"png":true}},"visacheckout":{"logo":{"svg":false,"png":true},"icon":{"svg":false,"png":true}},"hkma_fps":{"logo":{"svg":false,"png":true},"icon":{"svg":false,"png":true}},"petrolimex_bank":{"logo":{"svg":false,"png":true},"icon":{"svg":false,"png":true}},"airtel_money":{"logo":{"svg":false,"png":true},"icon":{"svg":false,"png":true}},"selcom":{"logo":{"svg":false,"png":true},"icon":{"svg":false,"png":true}},"duitnow":{"logo":{"svg":false,"png":true},"icon":{"svg":false,"png":true}},"mifinity":{"logo":{"svg":true,"png":false},"icon":{"svg":true,"png":false}},"bank_of_india":{"logo":{"svg":true,"png":false},"icon":{"svg":true,"png":false}},"banco_de_credito":{"logo":{"svg":false,"png":true},"icon":{"svg":false,"png":true}},"linkaja":{"icon":{"svg":false,"png":true},"logo":{"svg":true,"png":false}},"kwangju_bank":{"logo":{"svg":false,"png":true},"icon":{"svg":false,"png":true}},"tambo_cash":{"logo":{"svg":false,"png":true},"icon":{"svg":false,"png":true}},"farmacias_santa_maria_cash":{"logo":{"svg":false,"png":true},"icon":{"svg":false,"png":true}},"china_postal_savings_bank":{"logo":{"svg":false,"png":true},"icon":{"svg":true,"png":false}},"shanghai_pudong_development_bank":{"logo":{"svg":false,"png":true},"icon":{"svg":true,"png":false}},"banco_ciudad":{"logo":{"svg":false,"png":true},"icon":{"svg":false,"png":true}},"wupay":{"logo":{"svg":false,"png":true},"icon":{"svg":false,"png":true}},"yes_bank":{"logo":{"svg":true,"png":false},"icon":{"svg":true,"png":false}},"Self service kiosk Ukraine":{"logo":{"svg":false,"png":true},"icon":{"svg":false,"png":true}},"truevo":{"logo":{"svg":false,"png":true},"icon":{"svg":false,"png":true}},"peela":{"logo":{"svg":false,"png":true},"icon":{"svg":false,"png":true}},"galicia":{"logo":{"svg":false,"png":true},"icon":{"svg":false,"png":true}},"paysafecard":{"logo":{"svg":true,"png":false},"icon":{"svg":true,"png":false}},"ziraat_bankasi":{"logo":{"svg":false,"png":true},"icon":{"svg":false,"png":true}},"bkmexpress":{"logo":{"svg":false,"png":true},"icon":{"svg":false,"png":true}},"Self service kiosk South Africa":{"logo":{"svg":false,"png":true},"icon":{"svg":false,"png":true}},"lien_viet_post_bank":{"logo":{"svg":false,"png":true},"icon":{"svg":false,"png":true}},"elektronischeslastschriftverfahren":{"logo":{"svg":false,"png":true},"icon":{"svg":false,"png":true}},"ecoineu":{"logo":{"svg":false,"png":true},"icon":{"svg":false,"png":true}},"newera_payment_technologies_ltd_bazpayuah":{"logo":{"svg":true,"png":false},"icon":{"svg":true,"png":false}},"viabalotoonline":{"logo":{"svg":true,"png":false},"icon":{"svg":true,"png":false}},"trustly":{"logo":{"svg":true,"png":false},"icon":{"svg":true,"png":false}},"resursbank":{"logo":{"svg":true,"png":false},"icon":{"svg":true,"png":false}},"alandsbanken":{"logo":{"svg":false,"png":true},"icon":{"svg":false,"png":true}},"smsbilling":{"logo":{"svg":false,"png":true},"icon":{"svg":false,"png":true}},"papaya":{"logo":{"svg":false,"png":true},"icon":{"svg":false,"png":true}},"sepadirectdebit":{"logo":{"svg":true,"png":false},"icon":{"svg":true,"png":false}},"handelsbanken":{"logo":{"svg":false,"png":true},"icon":{"svg":false,"png":true}},"upi_qr":{"logo":{"svg":false,"png":true},"icon":{"svg":false,"png":true}},"mg_bank_saemmul":{"logo":{"svg":false,"png":true},"icon":{"svg":false,"png":true}},"au_small_finance_bank":{"logo":{"svg":false,"png":true},"icon":{"svg":false,"png":true}},"ocean_bank":{"logo":{"svg":false,"png":true},"icon":{"svg":false,"png":true}},"walmart":{"logo":{"svg":true,"png":false},"icon":{"svg":true,"png":false}},"unibank_kommersiya_banki":{"logo":{"svg":false,"png":true},"icon":{"svg":false,"png":true}},"mtn":{"logo":{"svg":true,"png":false},"icon":{"svg":true,"png":false}},"payment_card_crypto":{"logo":{"svg":true,"png":false},"icon":{"svg":true,"png":false}},"wave":{"logo":{"svg":false,"png":true},"icon":{"svg":false,"png":true}},"coinspaid":{"logo":{"svg":false,"png":true},"icon":{"svg":false,"png":true}},"tnm":{"logo":{"svg":true,"png":false},"icon":{"svg":true,"png":false}},"mastercard":{"logo":{"svg":true,"png":false},"icon":{"svg":true,"png":false}},"amazon_pay":{"logo":{"svg":true,"png":false},"icon":{"svg":true,"png":false}},"picpay":{"logo":{"svg":true,"png":false},"icon":{"svg":true,"png":false}},"tamilnad_mercantile_bank_india":{"logo":{"svg":false,"png":true},"icon":{"svg":false,"png":true}},"fastcheckoutmultisafepay":{"logo":{"svg":false,"png":true},"icon":{"svg":false,"png":true}},"hdfc_bank":{"logo":{"svg":true,"png":false},"icon":{"svg":true,"png":false}},"scb_bank":{"logo":{"svg":false,"png":true},"icon":{"svg":false,"png":true}},"bkash_limited":{"logo":{"svg":false,"png":true},"icon":{"svg":false,"png":true}},"tapiola":{"logo":{"svg":false,"png":true},"icon":{"svg":false,"png":true}},"asdasda":{"logo":{"svg":true,"png":true}},"paykwik":{"icon":{"svg":false,"png":true}},"kievstar":{"logo":{"svg":false,"png":true},"icon":{"svg":false,"png":true}},"bbva_frances":{"logo":{"svg":false,"png":true},"icon":{"svg":false,"png":true}},"farmaciasdelahorroalternativecashpaymentmethodsmexico":{"logo":{"svg":false,"png":true},"icon":{"svg":false,"png":true}},"liqpay":{"logo":{"svg":true,"png":false},"icon":{"svg":true,"png":false}},"bank_central_asia":{"logo":{"svg":true,"png":false},"icon":{"svg":true,"png":false}},"gcash":{"logo":{"svg":false,"png":true},"icon":{"svg":false,"png":true}},"spenn":{"logo":{"svg":false,"png":true},"icon":{"svg":false,"png":true}},"fups":{"logo":{"svg":false,"png":true},"icon":{"svg":false,"png":true}},"bitexpro_wallet":{"logo":{"svg":false,"png":true},"icon":{"svg":false,"png":true}},"shift4":{"icon":{"svg":false,"png":true},"logo":{"svg":true,"png":false}},"ing_group_bank":{"logo":{"svg":false,"png":true},"icon":{"svg":false,"png":true}},"inpay":{"logo":{"svg":false,"png":true},"icon":{"svg":false,"png":true}},"viber":{"logo":{"svg":false,"png":true},"icon":{"svg":false,"png":true}},"famsaalternativecashpaymentmethodsmexico":{"logo":{"svg":false,"png":true},"icon":{"svg":false,"png":true}},"bancopopular":{"logo":{"svg":false,"png":true},"icon":{"svg":false,"png":true}},"papara":{"logo":{"svg":true,"png":false},"icon":{"svg":true,"png":false}},"paytm":{"logo":{"svg":true,"png":false},"icon":{"svg":true,"png":false}},"rcbcoverthecounteronlinebankdeposit":{"logo":{"svg":false,"png":true},"icon":{"svg":false,"png":true}},"tinkoff":{"logo":{"svg":false,"png":true},"icon":{"svg":false,"png":true}},"ssk":{"logo":{"svg":false,"png":true},"icon":{"svg":false,"png":true}},"indian_overseas_bank":{"logo":{"svg":false,"png":true},"icon":{"svg":false,"png":true}},"viet_a_bank":{"logo":{"svg":false,"png":true},"icon":{"svg":false,"png":true}},"dong_a_bank":{"logo":{"svg":false,"png":true},"icon":{"svg":false,"png":true}},"caja_tacna_cash":{"logo":{"svg":false,"png":true},"icon":{"svg":false,"png":true}},"agri_bank":{"logo":{"svg":false,"png":true},"icon":{"svg":false,"png":true}},"applepay_crypto":{"logo":{"svg":true,"png":false},"icon":{"svg":true,"png":false}},"moov":{"logo":{"svg":false,"png":true},"icon":{"svg":false,"png":true}},"shb_bank":{"logo":{"svg":false,"png":true},"icon":{"svg":false,"png":true}},"walletone":{"logo":{"svg":false,"png":true},"icon":{"svg":false,"png":true}},"abaqoos":{"logo":{"svg":false,"png":true},"icon":{"svg":false,"png":true}},"gcash_qr":{"logo":{"svg":false,"png":true},"icon":{"svg":false,"png":true}},"aura":{"logo":{"svg":false,"png":true},"icon":{"svg":false,"png":true}},"central_bank_of_india":{"logo":{"svg":false,"png":true},"icon":{"svg":false,"png":true}},"public_bank_berhad":{"logo":{"svg":false,"png":true},"icon":{"svg":false,"png":true}},"banktransfer":{"logo":{"svg":true,"png":true},"icon":{"svg":true,"png":false}},"vodacom":{"logo":{"svg":false,"png":true},"icon":{"svg":false,"png":true}},"argencard":{"logo":{"svg":false,"png":true},"icon":{"svg":false,"png":true}},"privatbank_ssk":{"logo":{"svg":false,"png":true},"icon":{"svg":false,"png":true}},"zamtel":{"logo":{"svg":false,"png":true},"icon":{"svg":false,"png":true}},"banco_bci":{"logo":{"svg":false,"png":true},"icon":{"svg":false,"png":true}},"newera_payment_technologies_ltd_bazpay":{"logo":{"svg":true,"png":false},"icon":{"svg":true,"png":false}},"americanexpress":{"logo":{"svg":true,"png":false},"icon":{"svg":true,"png":false}},"googlepay_crypto":{"logo":{"svg":true,"png":false},"icon":{"svg":true,"png":false}},"m_pesa":{"logo":{"svg":false,"png":true},"icon":{"svg":false,"png":true}},"digital_cash":{"logo":{"svg":false,"png":true},"icon":{"svg":false,"png":true}},"faster_payments":{"logo":{"svg":true,"png":false},"icon":{"svg":true,"png":false}},"ethereum":{"logo":{"svg":true,"png":false},"icon":{"svg":true,"png":false}},"cooperative_bank":{"logo":{"svg":false,"png":true},"icon":{"svg":false,"png":true}},"eos":{"logo":{"svg":false,"png":true},"icon":{"svg":false,"png":true}},"sbp":{"logo":{"svg":true,"png":false},"icon":{"svg":true,"png":false}},"industrial_bank_of_korea":{"logo":{"svg":true,"png":false},"icon":{"svg":true,"png":false}},"binance_coin":{"logo":{"svg":true,"png":false},"icon":{"svg":true,"png":false}},"dogecoin":{"logo":{"svg":true,"png":false},"icon":{"svg":true,"png":false}},"hong_leong_bank":{"logo":{"svg":true,"png":false},"icon":{"svg":true,"png":false}},"ssk_md":{"logo":{"svg":false,"png":true},"icon":{"svg":false,"png":true}},"tigo":{"logo":{"svg":false,"png":true},"icon":{"svg":false,"png":true}},"spei":{"logo":{"svg":true,"png":false},"icon":{"svg":true,"png":false}},"vrb_bank":{"logo":{"svg":false,"png":true},"icon":{"svg":false,"png":true}},"nordea":{"logo":{"svg":false,"png":true},"icon":{"svg":false,"png":true}},"advcash_wallet_email":{"logo":{"svg":true,"png":false},"icon":{"svg":true,"png":false}},"belfiusdirectnet":{"logo":{"svg":false,"png":true},"icon":{"svg":false,"png":true}},"dokuwallet":{"logo":{"svg":false,"png":true},"icon":{"svg":false,"png":true}},"momopay":{"logo":{"svg":false,"png":true},"icon":{"svg":true,"png":true}},"visa_mastercard":{"icon":{"svg":false,"png":true}},"kookmin_bank":{"logo":{"svg":true,"png":false},"icon":{"svg":true,"png":false}},"hd_bank":{"logo":{"svg":false,"png":true},"icon":{"svg":false,"png":true}},"chainlink":{"logo":{"svg":false,"png":true},"icon":{"svg":false,"png":true}},"caja_huancayo_cash":{"logo":{"svg":false,"png":true},"icon":{"svg":false,"png":true}},"sofortuberweisung":{"logo":{"svg":true,"png":false},"icon":{"svg":true,"png":false}},"epayua":{"logo":{"svg":false,"png":true},"icon":{"svg":false,"png":true}},"ssk_by":{"logo":{"svg":false,"png":true},"icon":{"svg":false,"png":true}},"cardpay":{"logo":{"svg":true,"png":false},"icon":{"svg":true,"png":false}},"rhb_bank_fpx":{"logo":{"svg":true,"png":false},"icon":{"svg":true,"png":false}},"omllvcb_bank":{"logo":{"svg":false,"png":true},"icon":{"svg":false,"png":true}},"oxxo_cash":{"logo":{"svg":false,"png":true},"icon":{"svg":false,"png":true}},"toditocash":{"logo":{"svg":false,"png":true},"icon":{"svg":false,"png":true}},"bankzachodniwbk":{"logo":{"svg":false,"png":true},"icon":{"svg":false,"png":true}},"banklink":{"logo":{"svg":false,"png":true},"icon":{"svg":false,"png":true}},"bank_transfer_aggregated":{"logo":{"svg":true,"png":false},"icon":{"svg":true,"png":false}},"caja_desarrollo_cash":{"logo":{"svg":false,"png":true},"icon":{"svg":false,"png":true}},"sberonline":{"logo":{"svg":true,"png":false},"icon":{"svg":true,"png":false}},"sensebank":{"logo":{"svg":false,"png":true},"icon":{"svg":false,"png":true}},"cartasi":{"logo":{"svg":false,"png":true},"icon":{"svg":false,"png":true}},"fundacion_genesis_cash":{"logo":{"svg":false,"png":true},"icon":{"svg":false,"png":true}},"krungthaibanknetbanking":{"logo":{"svg":false,"png":true},"icon":{"svg":false,"png":true}},"billsafe":{"logo":{"svg":false,"png":true},"icon":{"svg":false,"png":true}},"budpay":{"logo":{"svg":false,"png":true},"icon":{"svg":false,"png":true}},"thaimilitarybanktmbnetbanking":{"logo":{"svg":false,"png":true},"icon":{"svg":false,"png":true}},"account2account":{"logo":{"svg":false,"png":true},"icon":{"svg":false,"png":true}},"googlepay":{"logo":{"svg":true,"png":false},"icon":{"svg":true,"png":false}},"santander_supernet":{"logo":{"svg":true,"png":false},"icon":{"svg":true,"png":false}},"acceptemail":{"logo":{"svg":false,"png":true},"icon":{"svg":false,"png":true}},"pep":{"logo":{"svg":false,"png":true},"icon":{"svg":false,"png":true}},"billmelater":{"logo":{"svg":false,"png":true},"icon":{"svg":false,"png":true}},"nagad_wallet":{"logo":{"svg":false,"png":true},"icon":{"svg":false,"png":true}},"citibank_turkey":{"logo":{"svg":true,"png":false},"icon":{"svg":true,"png":false}},"bankofchinanetbanking":{"logo":{"svg":false,"png":true},"icon":{"svg":false,"png":true}},"punjab_sind_bank":{"logo":{"svg":false,"png":true},"icon":{"svg":false,"png":true}},"tele2ru":{"logo":{"svg":true,"png":false},"icon":{"svg":true,"png":false}},"payfix":{"logo":{"svg":false,"png":true},"icon":{"svg":false,"png":true}},"russianpost":{"logo":{"svg":false,"png":true},"icon":{"svg":false,"png":true}},"payment_card_token":{"logo":{"svg":true,"png":false},"icon":{"svg":true,"png":false}},"clickandbuy":{"logo":{"svg":false,"png":true},"icon":{"svg":false,"png":true}},"icici_bank":{"logo":{"svg":true,"png":false},"icon":{"svg":true,"png":false}},"discover":{"logo":{"svg":true,"png":false},"icon":{"svg":true,"png":false}},"osuuspankki":{"logo":{"svg":false,"png":true},"icon":{"svg":false,"png":true}},"dragontech":{"logo":{"svg":false,"png":true},"icon":{"svg":false,"png":true}},"inghomepay":{"logo":{"svg":false,"png":true},"icon":{"svg":false,"png":true}},"Self service kiosk Tajikistan":{"logo":{"svg":false,"png":true},"icon":{"svg":false,"png":true}},"card":{"icon":{"svg":true,"png":true},"logo":{"svg":true,"png":false}},"south_indian_bank":{"logo":{"svg":false,"png":true},"icon":{"svg":false,"png":true}},"astropaycash":{"logo":{"svg":true,"png":false},"icon":{"svg":true,"png":false}},"ideal":{"logo":{"svg":true,"png":false},"icon":{"svg":true,"png":false}},"pagseguro":{"logo":{"svg":false,"png":true},"icon":{"svg":false,"png":true}},"pay_id":{"logo":{"svg":true,"png":false},"icon":{"svg":true,"png":false}},"pix":{"logo":{"svg":true,"png":false},"icon":{"svg":true,"png":false}},"sea_bank":{"logo":{"svg":false,"png":true},"icon":{"svg":false,"png":true}},"cabal":{"logo":{"svg":false,"png":true},"icon":{"svg":false,"png":true}},"safetypay":{"logo":{"svg":false,"png":true},"icon":{"svg":false,"png":true}},"commonwealth_bank":{"logo":{"svg":true,"png":false},"icon":{"svg":true,"png":false}},"octopuscardonlinepaymentservice":{"logo":{"svg":false,"png":true},"icon":{"svg":false,"png":true}},"paydirektalternativepaymentmethodgermany":{"logo":{"svg":false,"png":true},"icon":{"svg":false,"png":true}},"libertybank":{"logo":{"svg":false,"png":true},"icon":{"svg":false,"png":true}},"bank_negara_indonesia":{"logo":{"svg":true,"png":false},"icon":{"svg":true,"png":false}},"tpbank":{"logo":{"svg":false,"png":true},"icon":{"svg":false,"png":true}},"paymer":{"logo":{"svg":false,"png":true},"icon":{"svg":false,"png":true}},"truemoney":{"logo":{"svg":false,"png":true},"icon":{"svg":false,"png":true}},"bdooverthecounterofflinebankdeposit":{"logo":{"svg":false,"png":true},"icon":{"svg":false,"png":true}},"acb_bank":{"logo":{"svg":true,"png":false},"icon":{"svg":true,"png":false}},"farmacia_del_ahorro":{"logo":{"svg":true,"png":false},"icon":{"svg":true,"png":false}},"public_bank_vietnam":{"logo":{"svg":false,"png":true},"icon":{"svg":false,"png":true}},"farmaciasdelahorro":{"logo":{"svg":true,"png":false},"icon":{"svg":true,"png":false}},"sbrebank":{"logo":{"svg":false,"png":true},"icon":{"svg":false,"png":true}},"indian_bank":{"logo":{"svg":true,"png":false},"icon":{"svg":true,"png":false}},"paysafecash":{"logo":{"svg":true,"png":false},"icon":{"svg":true,"png":false}},"serve":{"logo":{"svg":false,"png":true},"icon":{"svg":false,"png":true}},"postfinancecard":{"logo":{"svg":false,"png":true},"icon":{"svg":false,"png":true}},"bank_transfer_klarna":{"logo":{"svg":true,"png":false},"icon":{"svg":true,"png":false}},"slovenskasporitelna":{"logo":{"svg":false,"png":true},"icon":{"svg":false,"png":true}},"mtn_group":{"logo":{"svg":false,"png":true},"icon":{"svg":false,"png":true}},"rapidtransfer":{"logo":{"svg":false,"png":true},"icon":{"svg":false,"png":true}},"mybank2":{"logo":{"svg":false,"png":true},"icon":{"svg":false,"png":true}},"emanat":{"logo":{"svg":false,"png":true},"icon":{"svg":false,"png":true}},"union_bank_of_india":{"logo":{"svg":true,"png":false},"icon":{"svg":true,"png":false}},"yandexmoney":{"logo":{"svg":true,"png":false},"icon":{"svg":true,"png":false}},"payeer":{"icon":{"svg":false,"png":true},"logo":{"svg":true,"png":false}},"vnpay_qr":{"logo":{"svg":false,"png":true},"icon":{"svg":false,"png":true}},"banco_credicoop":{"logo":{"svg":false,"png":true},"icon":{"svg":false,"png":true}},"upi_aggregated":{"logo":{"svg":true,"png":false},"icon":{"svg":true,"png":false}},"everi":{"logo":{"svg":false,"png":true},"icon":{"svg":false,"png":true}},"sepa_transfer_crypto":{"logo":{"svg":true,"png":false},"icon":{"svg":true,"png":false}},"bancoitau":{"logo":{"svg":false,"png":true},"icon":{"svg":false,"png":true}},"oxxoalternativecashpaymentmethodsmexico":{"logo":{"svg":false,"png":true},"icon":{"svg":false,"png":true}},"dinersclub":{"logo":{"svg":true,"png":false},"icon":{"svg":true,"png":false}},"danskebank":{"logo":{"svg":false,"png":true},"icon":{"svg":false,"png":true}},"epaybg":{"logo":{"svg":true,"png":false},"icon":{"svg":true,"png":false}},"bitexpro":{"logo":{"svg":false,"png":true},"icon":{"svg":false,"png":true}},"vp_bank":{"logo":{"svg":false,"png":true},"icon":{"svg":false,"png":true}},"csob":{"logo":{"svg":false,"png":true},"icon":{"svg":false,"png":true}},"visadebit":{"logo":{"svg":false,"png":true},"icon":{"svg":false,"png":true}},"ocb_bank":{"logo":{"svg":false,"png":true},"icon":{"svg":false,"png":true}},"upi_crypto":{"logo":{"svg":true,"png":false},"icon":{"svg":true,"png":false}},"magna":{"logo":{"svg":true,"png":false},"icon":{"svg":true,"png":false}},"revolut_bank":{"logo":{"svg":false,"png":true},"icon":{"svg":false,"png":true}},"may_bank":{"logo":{"svg":true,"png":false},"icon":{"svg":true,"png":false}},"bigconlinepayment":{"logo":{"svg":false,"png":true},"icon":{"svg":false,"png":true}},"kasikornbankkbanknetbanking":{"logo":{"svg":false,"png":true},"icon":{"svg":false,"png":true}},"mb_bank":{"logo":{"svg":false,"png":true},"icon":{"svg":false,"png":true}},"sepa_transfer":{"logo":{"svg":true,"png":false},"icon":{"svg":true,"png":false}},"karnataka_bank":{"logo":{"svg":true,"png":false},"icon":{"svg":true,"png":false}},"przelewy24":{"logo":{"svg":false,"png":true},"icon":{"svg":false,"png":true}},"rbl_bank":{"logo":{"svg":false,"png":true},"icon":{"svg":false,"png":true}},"vubbanka":{"logo":{"svg":false,"png":true},"icon":{"svg":false,"png":true}},"banrisulbanricompras":{"logo":{"svg":false,"png":true},"icon":{"svg":false,"png":true}},"cardano":{"icon":{"svg":true,"png":false}}}